Workbook

Sheet 填寫說明
A1: 文化部臺灣手語語料庫｜人工資料校訂表
A3: 項目 | B3: 填寫方式
A4: 本表筆數 | B4: 5125
A5: 評估範圍 | B5: 中文語意，以及 Gloss 的詞彙與語序。
A6: 主審判定 | B6: 每列只選：通過／需更正／排除／需複審。
A7: 通過 | B7: 原始中文與原始 Gloss 可直接作為 Text→Gloss 訓練資料。
A8: 需更正 | B8: 填問題類型、更正 Gloss 與理由；只有中文也需修改時才填更正中文。
A9: 排除 | B9: 填問題類型與理由；該列不會進入訓練資料。
A10: 需複審 | B10: 主審無法確定時選此項，再由第二位評估者填複審欄。
A11: 需影片確認 | B11: NMS、手形或動作方向不確定時選「是」；不阻擋文字層 Text→Gloss 校訂。
A12: 可填區域 | B12: 只填黃色欄 J:S；灰色 A:I 是原始資料，藍色 T:X 由公式產生。
A13: 姓名與日期 | B13: 本表不包含主審姓名、主審日期、複審姓名或複審日期欄位。
A15: 判定範例 | B15: 主審判定 | C15: 問題類型 | D15: 更正中文 | E15: 更正Gloss | F15: 更正理由
A16: 無問題 | B16: 通過
A17: Gloss 語序需修正 | B17: 需更正 | C17: Gloss語序錯誤 | E17: 學校/我/去 | F17: 主題應前置
A18: 資料無法使用 | B18: 排除 | C18: 中文與Gloss不對應 | F18: 無法由現有資訊修正

Sheet 人工校訂
A1: 穩定ID | B1: 重複來源ID | C1: 資料來源 | D1: 來源子類型 | E1: 原始中文 | F1: 原始Gloss | G1: 來源說明 | H1: 影片或文獻連結 | I1: 原始資料指紋 | J1: 主審判定 | K1: 問題類型 | L1: 更正中文 | M1: 更正Gloss | N1: 更正理由 | O1: 需影片確認 | P1: 複審判定 | Q1: 複審更正中文 | R1: 複審更正Gloss | S1: 複審意見 | T1: 最終判定 | U1: 最終中文 | V1: 最終Gloss | W1: 可匯入訓練 | X1: 資料檢查結果
A2: TC00001 | B2: TC00001 | C2: 文化部臺灣手語語料庫 | D2: 公共服務 | E2: 我的朋友半年前突然車禍， | F2: 我/朋友/六個月/以前/突然/車禍 | G2: G2D1P1/a81｜篇章1段落1｜臺灣手語語料庫（測試版），文化部，https://tslcorpus.moc.gov.tw/ | H2: https://tslcorpus.moc.gov.tw/upload/24/web/video/Bphwq023LKHuHx1y.mp4 | I2: 38a9fd017cf4d46acddd066cf0b278cfeb8cc7617defe5fc55d1dd15449bf5da | J2: 通過 | O2: 否 | T2: =IF(J2="","未填",IF(J2="需複審",IF(OR(P2="",P2="仍需複審"),"待複審",P2),J2)) -> 通過 | U2: =IF(T2="通過",E2,IF(T2="需更正",IF(J2="需複審",IF(Q2="",E2,Q2),IF(L2="",E2,L2)),"")) -> 我的朋友半年前突然車禍， | V2: =IF(T2="通過",F2,IF(T2="需更正",IF(J2="需複審",R2,M2),"")) -> 我/朋友/六個月/以前/突然/車禍 | W2: =IF(AND(OR(T2="通過",AND(T2="需更正",V2<>"")),X2="通過"),"是","否") -> 是 | X2: =IF(J2="","未填",IF(AND(J2="需複審",OR(P2="",P2="仍需複審")),"待複審",IF(OR(AND(J2="需更正",K2=""),AND(J2="需更正",M2=""),AND(J2="需更正",N2=""),AND(J2="排除",OR(K2="",N2="")),AND(J2="需複審",P2="需更正",R2=""),AND(J2="需複審",P2="需更正",S2=""),AND(J2="需複審",P2="排除",S2="")),"錯誤：請補齊必填欄位","通過"))) -> 通過
A3: TC00002 | B3: TC00002 | C3: 文化部臺灣手語語料庫 | D3: 公共服務 | E3: 造成雙耳極重度的聽損。 | F3: 雙耳/聽損/程度/重/很 | G3: G2D1P1/a82｜篇章1段落1｜臺灣手語語料庫（測試版），文化部，https://tslcorpus.moc.gov.tw/ | H3: https://tslcorpus.moc.gov.tw/upload/24/web/video/Bphwq023LKHuHx1y.mp4 | I3: 0d7bf9931bb67b32e48b696c05f5bd4e4a11435db9941f8fc5563698d1c894b4 | J3: 通過 | O3: 否 | T3: =IF(J3="","未填",IF(J3="需複審",IF(OR(P3="",P3="仍需複審"),"待複審",P3),J3)) -> 通過 | U3: =IF(T3="通過",E3,IF(T3="需更正",IF(J3="需複審",IF(Q3="",E3,Q3),IF(L3="",E3,L3)),"")) -> 造成雙耳極重度的聽損。 | V3: =IF(T3="通過",F3,IF(T3="需更正",IF(J3="需複審",R3,M3),"")) -> 雙耳/聽損/程度/重/很 | W3: =IF(AND(OR(T3="通過",AND(T3="需更正",V3<>"")),X3="通過"),"是","否") -> 是 | X3: =IF(J3="","未填",IF(AND(J3="需複審",OR(P3="",P3="仍需複審")),"待複審",IF(OR(AND(J3="需更正",K3=""),AND(J3="需更正",M3=""),AND(J3="需更正",N3=""),AND(J3="排除",OR(K3="",N3="")),AND(J3="需複審",P3="需更正",R3=""),AND(J3="需複審",P3="需更正",S3=""),AND(J3="需複審",P3="排除",S3="")),"錯誤：請補齊必填欄位","通過"))) -> 通過
A4: TC00003 | B4: TC00003 | C4: 文化部臺灣手語語料庫 | D4: 公共服務 | E4: 他在醫院治療期間，發現自己無法聽見。 | F4: 他/醫院/治療/期間/發現/自己/聽/沒辦法 | G4: G2D1P1/a83｜篇章1段落1｜臺灣手語語料庫（測試版），文化部，https://tslcorpus.moc.gov.tw/ | H4: https://tslcorpus.moc.gov.tw/upload/24/web/video/Bphwq023LKHuHx1y.mp4 | I4: b4a42ec76a4b5e43fd468dbd60e30e8e39e646cf6cca6fff6108fec272c670c3 | J4: 通過 | O4: 否 | T4: =IF(J4="","未填",IF(J4="需複審",IF(OR(P4="",P4="仍需複審"),"待複審",P4),J4)) -> 通過 | U4: =IF(T4="通過",E4,IF(T4="需更正",IF(J4="需複審",IF(Q4="",E4,Q4),IF(L4="",E4,L4)),"")) -> 他在醫院治療期間，發現自己無法聽見。 | V4: =IF(T4="通過",F4,IF(T4="需更正",IF(J4="需複審",R4,M4),"")) -> 他/醫院/治療/期間/發現/自己/聽/沒辦法 | W4: =IF(AND(OR(T4="通過",AND(T4="需更正",V4<>"")),X4="通過"),"是","否") -> 是 | X4: =IF(J4="","未填",IF(AND(J4="需複審",OR(P4="",P4="仍需複審")),"待複審",IF(OR(AND(J4="需更正",K4=""),AND(J4="需更正",M4=""),AND(J4="需更正",N4=""),AND(J4="排除",OR(K4="",N4="")),AND(J4="需複審",P4="需更正",R4=""),AND(J4="需複審",P4="需更正",S4=""),AND(J4="需複審",P4="排除",S4="")),"錯誤：請補齊必填欄位","通過"))) -> 通過
A5: TC00004 | B5: TC00004 | C5: 文化部臺灣手語語料庫 | D5: 公共服務 | E5: 聽力檢查證實右耳聽力為九十五分貝，左耳九十分貝， | F5: 聽力/檢查/證實/右耳/九十五/左耳/九十 | G5: G2D1P1/a84｜篇章1段落1｜臺灣手語語料庫（測試版），文化部，https://tslcorpus.moc.gov.tw/ | H5: https://tslcorpus.moc.gov.tw/upload/24/web/video/Bphwq023LKHuHx1y.mp4 | I5: c25131587947a4eee8157a680927da8ab424e37a74099cb84441eb3b69aa28d7 | J5: 通過 | O5: 否 | T5: =IF(J5="","未填",IF(J5="需複審",IF(OR(P5="",P5="仍需複審"),"待複審",P5),J5)) -> 通過 | U5: =IF(T5="通過",E5,IF(T5="需更正",IF(J5="需複審",IF(Q5="",E5,Q5),IF(L5="",E5,L5)),"")) -> 聽力檢查證實右耳聽力為九十五分貝，左耳九十分貝， | V5: =IF(T5="通過",F5,IF(T5="需更正",IF(J5="需複審",R5,M5),"")) -> 聽力/檢查/證實/右耳/九十五/左耳/九十 | W5: =IF(AND(OR(T5="通過",AND(T5="需更正",V5<>"")),X5="通過"),"是","否") -> 是 | X5: =IF(J5="","未填",IF(AND(J5="需複審",OR(P5="",P5="仍需複審")),"待複審",IF(OR(AND(J5="需更正",K5=""),AND(J5="需更正",M5=""),AND(J5="需更正",N5=""),AND(J5="排除",OR(K5="",N5="")),AND(J5="需複審",P5="需更正",R5=""),AND(J5="需複審",P5="需更正",S5=""),AND(J5="需複審",P5="排除",S5="")),"錯誤：請補齊必填欄位","通過"))) -> 通過
A6: TC00005 | B6: TC00005 | C6: 文化部臺灣手語語料庫 | D6: 公共服務 | E6: 聽損程度是極重度。 | F6: 聽損/程度/重/很/是 | G6: G2D1P1/a86｜篇章1段落1｜臺灣手語語料庫（測試版），文化部，https://tslcorpus.moc.gov.tw/ | H6: https://tslcorpus.moc.gov.tw/upload/24/web/video/Bphwq023LKHuHx1y.mp4 | I6: 659e6bbe9a81387cb38be58390154b2cbe9700f890b110dee94d4c4cc6427a92 | J6: 通過 | O6: 否 | T6: =IF(J6="","未填",IF(J6="需複審",IF(OR(P6="",P6="仍需複審"),"待複審",P6),J6)) -> 通過 | U6: =IF(T6="通過",E6,IF(T6="需更正",IF(J6="需複審",IF(Q6="",E6,Q6),IF(L6="",E6,L6)),"")) -> 聽損程度是極重度。 | V6: =IF(T6="通過",F6,IF(T6="需更正",IF(J6="需複審",R6,M6),"")) -> 聽損/程度/重/很/是 | W6: =IF(AND(OR(T6="通過",AND(T6="需更正",V6<>"")),X6="通過"),"是","否") -> 是 | X6: =IF(J6="","未填",IF(AND(J6="需複審",OR(P6="",P6="仍需複審")),"待複審",IF(OR(AND(J6="需更正",K6=""),AND(J6="需更正",M6=""),AND(J6="需更正",N6=""),AND(J6="排除",OR(K6="",N6="")),AND(J6="需複審",P6="需更正",R6=""),AND(J6="需複審",P6="需更正",S6=""),AND(J6="需複審",P6="排除",S6="")),"錯誤：請補齊必填欄位","通過"))) -> 通過
A7: TC00006 | B7: TC00006 | C7: 文化部臺灣手語語料庫 | D7: 公共服務 | E7: 他治療三個月之後， 聽損情形依舊無法回復正常。 | F7: 他/治療/三個月/以後/聽損/依舊/聽人/回/沒辦法 | G7: G2D1P1/a87｜篇章1段落1｜臺灣手語語料庫（測試版），文化部，https://tslcorpus.moc.gov.tw/ | H7: https://tslcorpus.moc.gov.tw/upload/24/web/video/Bphwq023LKHuHx1y.mp4 | I7: 1b54157ddd287bf55249e56b116ef60e996919d66ebddd26c634a64483da4b2f | J7: 通過 | O7: 否 | T7: =IF(J7="","未填",IF(J7="需複審",IF(OR(P7="",P7="仍需複審"),"待複審",P7),J7)) -> 通過 | U7: =IF(T7="通過",E7,IF(T7="需更正",IF(J7="需複審",IF(Q7="",E7,Q7),IF(L7="",E7,L7)),"")) -> 他治療三個月之後， 聽損情形依舊無法回復正常。 | V7: =IF(T7="通過",F7,IF(T7="需更正",IF(J7="需複審",R7,M7),"")) -> 他/治療/三個月/以後/聽損/依舊/聽人/回/沒辦法 | W7: =IF(AND(OR(T7="通過",AND(T7="需更正",V7<>"")),X7="通過"),"是","否") -> 是 | X7: =IF(J7="","未填",IF(AND(J7="需複審",OR(P7="",P7="仍需複審")),"待複審",IF(OR(AND(J7="需更正",K7=""),AND(J7="需更正",M7=""),AND(J7="需更正",N7=""),AND(J7="排除",OR(K7="",N7="")),AND(J7="需複審",P7="需更正",R7=""),AND(J7="需複審",P7="需更正",S7=""),AND(J7="需複審",P7="排除",S7="")),"錯誤：請補齊必填欄位","通過"))) -> 通過
A8: TC00007 | B8: TC00007 | C8: 文化部臺灣手語語料庫 | D8: 休閒娛樂 | E8: 新店最近設立了一個陽光運動公園， | F8: 新店/陽光運動公園/最近 | G8: G1D1P1/a93｜篇章1段落1｜臺灣手語語料庫（測試版），文化部，https://tslcorpus.moc.gov.tw/ | H8: https://tslcorpus.moc.gov.tw/upload/24/web/video/US8fgOf7S1DnRtE8.mp4 | I8: e346be912956e7d8da63da416788580d3f0f05bcd3babf8b091af1825fe3e081 | J8: 需更正 | K8: 漏詞 | M8: 新店/陽光運動公園/最近/設立 | N8: 漏詞 | O8: 否 | T8: =IF(J8="","未填",IF(J8="需複審",IF(OR(P8="",P8="仍需複審"),"待複審",P8),J8)) -> 需更正 | U8: =IF(T8="通過",E8,IF(T8="需更正",IF(J8="需複審",IF(Q8="",E8,Q8),IF(L8="",E8,L8)),"")) -> 新店最近設立了一個陽光運動公園， | V8: =IF(T8="通過",F8,IF(T8="需更正",IF(J8="需複審",R8,M8),"")) -> 新店/陽光運動公園/最近/設立 | W8: =IF(AND(OR(T8="通過",AND(T8="需更正",V8<>"")),X8="通過"),"是","否") -> 是 | X8: =IF(J8="","未填",IF(AND(J8="需複審",OR(P8="",P8="仍需複審")),"待複審",IF(OR(AND(J8="需更正",K8=""),AND(J8="需更正",M8=""),AND(J8="需更正",N8=""),AND(J8="排除",OR(K8="",N8="")),AND(J8="需複審",P8="需更正",R8=""),AND(J8="需複審",P8="需更正",S8=""),AND(J8="需複審",P8="排除",S8="")),"錯誤：請補齊必填欄位","通過"))) -> 通過
A9: TC00008 | B9: TC00008 | C9: 文化部臺灣手語語料庫 | D9: 休閒娛樂 | E9: 我以前帶孩子去玩。 | F9: 設立/我/以前/孩子/帶/去/玩 | G9: G1D1P1/a94｜篇章1段落1｜臺灣手語語料庫（測試版），文化部，https://tslcorpus.moc.gov.tw/ | H9: https://tslcorpus.moc.gov.tw/upload/24/web/video/US8fgOf7S1DnRtE8.mp4 | I9: 601b03baf31f1a890a5b56e8427096ca8ff75c895ce5a09a1830d1b04afd08ae | J9: 需更正 | K9: 多餘詞 | M9: 我/以前/孩子/帶/去/玩 | N9: 多詞 | O9: 否 | T9: =IF(J9="","未填",IF(J9="需複審",IF(OR(P9="",P9="仍需複審"),"待複審",P9),J9)) -> 需更正 | U9: =IF(T9="通過",E9,IF(T9="需更正",IF(J9="需複審",IF(Q9="",E9,Q9),IF(L9="",E9,L9)),"")) -> 我以前帶孩子去玩。 | V9: =IF(T9="通過",F9,IF(T9="需更正",IF(J9="需複審",R9,M9),"")) -> 我/以前/孩子/帶/去/玩 | W9: =IF(AND(OR(T9="通過",AND(T9="需更正",V9<>"")),X9="通過"),"是","否") -> 是 | X9: =IF(J9="","未填",IF(AND(J9="需複審",OR(P9="",P9="仍需複審")),"待複審",IF(OR(AND(J9="需更正",K9=""),AND(J9="需更正",M9=""),AND(J9="需更正",N9=""),AND(J9="排除",OR(K9="",N9="")),AND(J9="需複審",P9="需更正",R9=""),AND(J9="需複審",P9="需更正",S9=""),AND(J9="需複審",P9="排除",S9="")),"錯誤：請補齊必填欄位","通過"))) -> 通過
A10: TC00009 | B10: TC00009 | C10: 文化部臺灣手語語料庫 | D10: 休閒娛樂 | E10: 我在公園往四處望去， | F10: 我/環視 | G10: G1D1P1/a95｜篇章1段落1｜臺灣手語語料庫（測試版），文化部，https://tslcorpus.moc.gov.tw/ | H10: https://tslcorpus.moc.gov.tw/upload/24/web/video/US8fgOf7S1DnRtE8.mp4 | I10: 7c8171e086cbe3fdf46328c7d0b2c0467697b7f2cb4e95259be6441866bca49a | J10: 通過 | O10: 否 | T10: =IF(J10="","未填",IF(J10="需複審",IF(OR(P10="",P10="仍需複審"),"待複審",P10),J10)) -> 通過 | U10: =IF(T10="通過",E10,IF(T10="需更正",IF(J10="需複審",IF(Q10="",E10,Q10),IF(L10="",E10,L10)),"")) -> 我在公園往四處望去， | V10: =IF(T10="通過",F10,IF(T10="需更正",IF(J10="需複審",R10,M10),"")) -> 我/環視 | W10: =IF(AND(OR(T10="通過",AND(T10="需更正",V10<>"")),X10="通過"),"是","否") -> 是 | X10: =IF(J10="","未填",IF(AND(J10="需複審",OR(P10="",P10="仍需複審")),"待複審",IF(OR(AND(J10="需更正",K10=""),AND(J10="需更正",M10=""),AND(J10="需更正",N10=""),AND(J10="排除",OR(K10="",N10="")),AND(J10="需複審",P10="需更正",R10=""),AND(J10="需複審",P10="需更正",S10=""),AND(J10="需複審",P10="排除",S10="")),"錯誤：請補齊必填欄位","通過"))) -> 通過
A11: TC00010 | B11: TC00010 | C11: 文化部臺灣手語語料庫 | D11: 休閒娛樂 | E11: 裡面鞦韆、溜滑梯、翹翹板、單槓等遊樂設施， | F11: 鞦韆/溜滑梯/翹翹板/單槓 | G11: G1D1P1/a607｜篇章1段落1｜臺灣手語語料庫（測試版），文化部，https://tslcorpus.moc.gov.tw/ | H11: https://tslcorpus.moc.gov.tw/upload/24/web/video/US8fgOf7S1DnRtE8.mp4 | I11: 71d94903ca749d9d54b7c5a5f23e18c1e954fb4421a3f5201bf840f189fc57f8 | J11: 通過 | O11: 否 | T11: =IF(J11="","未填",IF(J11="需複審",IF(OR(P11="",P11="仍需複審"),"待複審",P11),J11)) -> 通過 | U11: =IF(T11="通過",E11,IF(T11="需更正",IF(J11="需複審",IF(Q11="",E11,Q11),IF(L11="",E11,L11)),"")) -> 裡面鞦韆、溜滑梯、翹翹板、單槓等遊樂設施， | V11: =IF(T11="通過",F11,IF(T11="需更正",IF(J11="需複審",R11,M11),"")) -> 鞦韆/溜滑梯/翹翹板/單槓 | W11: =IF(AND(OR(T11="通過",AND(T11="需更正",V11<>"")),X11="通過"),"是","否") -> 是 | X11: =IF(J11="","未填",IF(AND(J11="需複審",OR(P11="",P11="仍需複審")),"待複審",IF(OR(AND(J11="需更正",K11=""),AND(J11="需更正",M11=""),AND(J11="需更正",N11=""),AND(J11="排除",OR(K11="",N11="")),AND(J11="需複審",P11="需更正",R11=""),AND(J11="需複審",P11="需更正",S11=""),AND(J11="需複審",P11="排除",S11="")),"錯誤：請補齊必填欄位","通過"))) -> 通過
A12: TC00011 | B12: TC00011 | C12: 文化部臺灣手語語料庫 | D12: 休閒娛樂 | E12: 應有盡有。 | F12: 各式各樣/有 | G12: G1D1P1/a608｜篇章1段落1｜臺灣手語語料庫（測試版），文化部，https://tslcorpus.moc.gov.tw/ | H12: https://tslcorpus.moc.gov.tw/upload/24/web/video/US8fgOf7S1DnRtE8.mp4 | I12: 7d22aaf0cb4fb4ef66f075908e3ebc5dc0de7141bc27f6c543e8191001499c94 | J12: 通過 | O12: 否 | T12: =IF(J12="","未填",IF(J12="需複審",IF(OR(P12="",P12="仍需複審"),"待複審",P12),J12)) -> 通過 | U12: =IF(T12="通過",E12,IF(T12="需更正",IF(J12="需複審",IF(Q12="",E12,Q12),IF(L12="",E12,L12)),"")) -> 應有盡有。 | V12: =IF(T12="通過",F12,IF(T12="需更正",IF(J12="需複審",R12,M12),"")) -> 各式各樣/有 | W12: =IF(AND(OR(T12="通過",AND(T12="需更正",V12<>"")),X12="通過"),"是","否") -> 是 | X12: =IF(J12="","未填",IF(AND(J12="需複審",OR(P12="",P12="仍需複審")),"待複審",IF(OR(AND(J12="需更正",K12=""),AND(J12="需更正",M12=""),AND(J12="需更正",N12=""),AND(J12="排除",OR(K12="",N12="")),AND(J12="需複審",P12="需更正",R12=""),AND(J12="需複審",P12="需更正",S12=""),AND(J12="需複審",P12="排除",S12="")),"錯誤：請補齊必填欄位","通過"))) -> 通過
A13: TC00012 | B13: TC00012 | C13: 文化部臺灣手語語料庫 | D13: 休閒娛樂 | E13: 這邊是坡道較短的溜滑梯， | F13: 這/溜滑梯/短 | G13: G1D1P1/a96｜篇章1段落1｜臺灣手語語料庫（測試版），文化部，https://tslcorpus.moc.gov.tw/ | H13: https://tslcorpus.moc.gov.tw/upload/24/web/video/US8fgOf7S1DnRtE8.mp4 | I13: 0e15a0e7b65a7d567f6139251b930006a4624c5efb193f1402799d24af1a4a86 | J13: 通過 | O13: 否 | T13: =IF(J13="","未填",IF(J13="需複審",IF(OR(P13="",P13="仍需複審"),"待複審",P13),J13)) -> 通過 | U13: =IF(T13="通過",E13,IF(T13="需更正",IF(J13="需複審",IF(Q13="",E13,Q13),IF(L13="",E13,L13)),"")) -> 這邊是坡道較短的溜滑梯， | V13: =IF(T13="通過",F13,IF(T13="需更正",IF(J13="需複審",R13,M13),"")) -> 這/溜滑梯/短 | W13: =IF(AND(OR(T13="通過",AND(T13="需更正",V13<>"")),X13="通過"),"是","否") -> 是 | X13: =IF(J13="","未填",IF(AND(J13="需複審",OR(P13="",P13="仍需複審")),"待複審",IF(OR(AND(J13="需更正",K13=""),AND(J13="需更正",M13=""),AND(J13="需更正",N13=""),AND(J13="排除",OR(K13="",N13="")),AND(J13="需複審",P13="需更正",R13=""),AND(J13="需複審",P13="需更正",S13=""),AND(J13="需複審",P13="排除",S13="")),"錯誤：請補齊必填欄位","通過"))) -> 通過
A14: TC00013 | B14: TC00013 | C14: 文化部臺灣手語語料庫 | D14: 休閒娛樂 | E14: 那邊是坡道較長較寬的溜滑梯。 | F14: 那/溜滑梯/長/寬大 | G14: G1D1P1/a609｜篇章1段落1｜臺灣手語語料庫（測試版），文化部，https://tslcorpus.moc.gov.tw/ | H14: https://tslcorpus.moc.gov.tw/upload/24/web/video/US8fgOf7S1DnRtE8.mp4 | I14: 179b2027530b28f066b1bacede3b3ab78e4be7cafe2c0480ca0c897decf4914c | J14: 通過 | O14: 否 | T14: =IF(J14="","未填",IF(J14="需複審",IF(OR(P14="",P14="仍需複審"),"待複審",P14),J14)) -> 通過 | U14: =IF(T14="通過",E14,IF(T14="需更正",IF(J14="需複審",IF(Q14="",E14,Q14),IF(L14="",E14,L14)),"")) -> 那邊是坡道較長較寬的溜滑梯。 | V14: =IF(T14="通過",F14,IF(T14="需更正",IF(J14="需複審",R14,M14),"")) -> 那/溜滑梯/長/寬大 | W14: =IF(AND(OR(T14="通過",AND(T14="需更正",V14<>"")),X14="通過"),"是","否") -> 是 | X14: =IF(J14="","未填",IF(AND(J14="需複審",OR(P14="",P14="仍需複審")),"待複審",IF(OR(AND(J14="需更正",K14=""),AND(J14="需更正",M14=""),AND(J14="需更正",N14=""),AND(J14="排除",OR(K14="",N14="")),AND(J14="需複審",P14="需更正",R14=""),AND(J14="需複審",P14="需更正",S14=""),AND(J14="需複審",P14="排除",S14="")),"錯誤：請補齊必填欄位","通過"))) -> 通過
A15: TC00014 | B15: TC00014 | C15: 文化部臺灣手語語料庫 | D15: 休閒娛樂 | E15: 此外還有一座用繩索編織而成的橋， | F15: 此外/還有/繩子/結繩/橋 | G15: G1D1P1/a97｜篇章1段落1｜臺灣手語語料庫（測試版），文化部，https://tslcorpus.moc.gov.tw/ | H15: https://tslcorpus.moc.gov.tw/upload/24/web/video/US8fgOf7S1DnRtE8.mp4 | I15: da54622c721a73b0854334a38abf4c710eb480d30e401cdcd3c10fd2ac2f1bdb | J15: 通過 | O15: 否 | T15: =IF(J15="","未填",IF(J15="需複審",IF(OR(P15="",P15="仍需複審"),"待複審",P15),J15)) -> 通過 | U15: =IF(T15="通過",E15,IF(T15="需更正",IF(J15="需複審",IF(Q15="",E15,Q15),IF(L15="",E15,L15)),"")) -> 此外還有一座用繩索編織而成的橋， | V15: =IF(T15="通過",F15,IF(T15="需更正",IF(J15="需複審",R15,M15),"")) -> 此外/還有/繩子/結繩/橋 | W15: =IF(AND(OR(T15="通過",AND(T15="需更正",V15<>"")),X15="通過"),"是","否") -> 是 | X15: =IF(J15="","未填",IF(AND(J15="需複審",OR(P15="",P15="仍需複審")),"待複審",IF(OR(AND(J15="需更正",K15=""),AND(J15="需更正",M15=""),AND(J15="需更正",N15=""),AND(J15="排除",OR(K15="",N15="")),AND(J15="需複審",P15="需更正",R15=""),AND(J15="需複審",P15="需更正",S15=""),AND(J15="需複審",P15="排除",S15="")),"錯誤：請補齊必填欄位","通過"))) -> 通過
A16: TC00015 | B16: TC00015 | C16: 文化部臺灣手語語料庫 | D16: 休閒娛樂 | E16: 小孩可以站在橋上雙手扶著繩索往前走。 | F16: 小孩/站上+橋/走+橋/兩邊繩索+扶 | G16: G1D1P1/a98｜篇章1段落1｜臺灣手語語料庫（測試版），文化部，https://tslcorpus.moc.gov.tw/ | H16: https://tslcorpus.moc.gov.tw/upload/24/web/video/US8fgOf7S1DnRtE8.mp4 | I16: d767bbe4f73dae232321336c3534d3cbd0abcfd050d61790090620019fd826e2 | J16: 通過 | O16: 否 | T16: =IF(J16="","未填",IF(J16="需複審",IF(OR(P16="",P16="仍需複審"),"待複審",P16),J16)) -> 通過 | U16: =IF(T16="通過",E16,IF(T16="需更正",IF(J16="需複審",IF(Q16="",E16,Q16),IF(L16="",E16,L16)),"")) -> 小孩可以站在橋上雙手扶著繩索往前走。 | V16: =IF(T16="通過",F16,IF(T16="需更正",IF(J16="需複審",R16,M16),"")) -> 小孩/站上+橋/走+橋/兩邊繩索+扶 | W16: =IF(AND(OR(T16="通過",AND(T16="需更正",V16<>"")),X16="通過"),"是","否") -> 是 | X16: =IF(J16="","未填",IF(AND(J16="需複審",OR(P16="",P16="仍需複審")),"待複審",IF(OR(AND(J16="需更正",K16=""),AND(J16="需更正",M16=""),AND(J16="需更正",N16=""),AND(J16="排除",OR(K16="",N16="")),AND(J16="需複審",P16="需更正",R16=""),AND(J16="需複審",P16="需更正",S16=""),AND(J16="需複審",P16="排除",S16="")),"錯誤：請補齊必填欄位","通過"))) -> 通過
A17: TC00016 | B17: TC00016 | C17: 文化部臺灣手語語料庫 | D17: 休閒娛樂 | E17: 我看到另一頭有個又大又寬的溜冰場， | F17: 我/看/溜冰場/那裡/大/寬大 | G17: G1D1P1/a99｜篇章1段落1｜臺灣手語語料庫（測試版），文化部，https://tslcorpus.moc.gov.tw/ | H17: https://tslcorpus.moc.gov.tw/upload/24/web/video/US8fgOf7S1DnRtE8.mp4 | I17: 7639140eac04acdf524591553cfa78062d51610b7bcea1f5f4c7922a2510569a | J17: 通過 | O17: 否 | T17: =IF(J17="","未填",IF(J17="需複審",IF(OR(P17="",P17="仍需複審"),"待複審",P17),J17)) -> 通過 | U17: =IF(T17="通過",E17,IF(T17="需更正",IF(J17="需複審",IF(Q17="",E17,Q17),IF(L17="",E17,L17)),"")) -> 我看到另一頭有個又大又寬的溜冰場， | V17: =IF(T17="通過",F17,IF(T17="需更正",IF(J17="需複審",R17,M17),"")) -> 我/看/溜冰場/那裡/大/寬大 | W17: =IF(AND(OR(T17="通過",AND(T17="需更正",V17<>"")),X17="通過"),"是","否") -> 是 | X17: =IF(J17="","未填",IF(AND(J17="需複審",OR(P17="",P17="仍需複審")),"待複審",IF(OR(AND(J17="需更正",K17=""),AND(J17="需更正",M17=""),AND(J17="需更正",N17=""),AND(J17="排除",OR(K17="",N17="")),AND(J17="需複審",P17="需更正",R17=""),AND(J17="需複審",P17="需更正",S17=""),AND(J17="需複審",P17="排除",S17="")),"錯誤：請補齊必填欄位","通過"))) -> 通過
A18: TC00017 | B18: TC00017 | C18: 文化部臺灣手語語料庫 | D18: 休閒娛樂 | E18: 溜冰的人很多， | F18: 人/多 | G18: G1D1P1/a100｜篇章1段落1｜臺灣手語語料庫（測試版），文化部，https://tslcorpus.moc.gov.tw/ | H18: https://tslcorpus.moc.gov.tw/upload/24/web/video/US8fgOf7S1DnRtE8.mp4 | I18: 0718741bf09c9984e6da9d98e051d52f3f71bafba86a9c32f89a2d1dcbcf249c | J18: 通過 | O18: 否 | T18: =IF(J18="","未填",IF(J18="需複審",IF(OR(P18="",P18="仍需複審"),"待複審",P18),J18)) -> 通過 | U18: =IF(T18="通過",E18,IF(T18="需更正",IF(J18="需複審",IF(Q18="",E18,Q18),IF(L18="",E18,L18)),"")) -> 溜冰的人很多， | V18: =IF(T18="通過",F18,IF(T18="需更正",IF(J18="需複審",R18,M18),"")) -> 人/多 | W18: =IF(AND(OR(T18="通過",AND(T18="需更正",V18<>"")),X18="通過"),"是","否") -> 是 | X18: =IF(J18="","未填",IF(AND(J18="需複審",OR(P18="",P18="仍需複審")),"待複審",IF(OR(AND(J18="需更正",K18=""),AND(J18="需更正",M18=""),AND(J18="需更正",N18=""),AND(J18="排除",OR(K18="",N18="")),AND(J18="需複審",P18="需更正",R18=""),AND(J18="需複審",P18="需更正",S18=""),AND(J18="需複審",P18="排除",S18="")),"錯誤：請補齊必填欄位","通過"))) -> 通過
A19: TC00018 | B19: TC00018 | C19: 文化部臺灣手語語料庫 | D19: 休閒娛樂 | E19: 但他們都會依序排隊。 | F19: 他們/排隊/按照/會 | G19: G1D1P1/a610｜篇章1段落1｜臺灣手語語料庫（測試版），文化部，https://tslcorpus.moc.gov.tw/ | H19: https://tslcorpus.moc.gov.tw/upload/24/web/video/US8fgOf7S1DnRtE8.mp4 | I19: 41d93ecb86baed358b626ac2a65b4031bd149b56abfd08f51677c53276bf5a77 | J19: 通過 | O19: 否 | T19: =IF(J19="","未填",IF(J19="需複審",IF(OR(P19="",P19="仍需複審"),"待複審",P19),J19)) -> 通過 | U19: =IF(T19="通過",E19,IF(T19="需更正",IF(J19="需複審",IF(Q19="",E19,Q19),IF(L19="",E19,L19)),"")) -> 但他們都會依序排隊。 | V19: =IF(T19="通過",F19,IF(T19="需更正",IF(J19="需複審",R19,M19),"")) -> 他們/排隊/按照/會 | W19: =IF(AND(OR(T19="通過",AND(T19="需更正",V19<>"")),X19="通過"),"是","否") -> 是 | X19: =IF(J19="","未填",IF(AND(J19="需複審",OR(P19="",P19="仍需複審")),"待複審",IF(OR(AND(J19="需更正",K19=""),AND(J19="需更正",M19=""),AND(J19="需更正",N19=""),AND(J19="排除",OR(K19="",N19="")),AND(J19="需複審",P19="需更正",R19=""),AND(J19="需複審",P19="需更正",S19=""),AND(J19="需複審",P19="排除",S19="")),"錯誤：請補齊必填欄位","通過"))) -> 通過
A20: TC00019 | B20: TC00019 | C20: 文化部臺灣手語語料庫 | D20: 身體醫療 | E20: 上星期六我和五六位朋友，一起前往陽明山爬山， | F20: 上週/星期六/朋友/五/六/一起/去/陽明山/爬山 | G20: G2D2P1/a98｜篇章1段落1｜臺灣手語語料庫（測試版），文化部，https://tslcorpus.moc.gov.tw/ | H20: https://tslcorpus.moc.gov.tw/upload/24/web/video/omvqLsk905tqXVMq.mp4 | I20: dbe2fabd5a68d12501b2fe80d5cd1d4b1724a6d0c8491d33a0ed73a26592284d | J20: 通過 | O20: 否 | T20: =IF(J20="","未填",IF(J20="需複審",IF(OR(P20="",P20="仍需複審"),"待複審",P20),J20)) -> 通過 | U20: =IF(T20="通過",E20,IF(T20="需更正",IF(J20="需複審",IF(Q20="",E20,Q20),IF(L20="",E20,L20)),"")) -> 上星期六我和五六位朋友，一起前往陽明山爬山， | V20: =IF(T20="通過",F20,IF(T20="需更正",IF(J20="需複審",R20,M20),"")) -> 上週/星期六/朋友/五/六/一起/去/陽明山/爬山 | W20: =IF(AND(OR(T20="通過",AND(T20="需更正",V20<>"")),X20="通過"),"是","否") -> 是 | X20: =IF(J20="","未填",IF(AND(J20="需複審",OR(P20="",P20="仍需複審")),"待複審",IF(OR(AND(J20="需更正",K20=""),AND(J20="需更正",M20=""),AND(J20="需更正",N20=""),AND(J20="排除",OR(K20="",N20="")),AND(J20="需複審",P20="需更正",R20=""),AND(J20="需複審",P20="需更正",S20=""),AND(J20="需複審",P20="排除",S20="")),"錯誤：請補齊必填欄位","通過"))) -> 通過
A21: TC00020 | B21: TC00020 | C21: 文化部臺灣手語語料庫 | D21: 身體醫療 | E21: 大家一起開心地出遊。 | F21: 我們/開心/出遊 | G21: G2D2P1/a99｜篇章1段落1｜臺灣手語語料庫（測試版），文化部，https://tslcorpus.moc.gov.tw/ | H21: https://tslcorpus.moc.gov.tw/upload/24/web/video/omvqLsk905tqXVMq.mp4 | I21: 394e5ebf49854514b2d468117730841c378bc4c4bcc7ae7f6065f0a4c95834f0 | J21: 通過 | O21: 否 | T21: =IF(J21="","未填",IF(J21="需複審",IF(OR(P21="",P21="仍需複審"),"待複審",P21),J21)) -> 通過 | U21: =IF(T21="通過",E21,IF(T21="需更正",IF(J21="需複審",IF(Q21="",E21,Q21),IF(L21="",E21,L21)),"")) -> 大家一起開心地出遊。 | V21: =IF(T21="通過",F21,IF(T21="需更正",IF(J21="需複審",R21,M21),"")) -> 我們/開心/出遊 | W21: =IF(AND(OR(T21="通過",AND(T21="需更正",V21<>"")),X21="通過"),"是","否") -> 是 | X21: =IF(J21="","未填",IF(AND(J21="需複審",OR(P21="",P21="仍需複審")),"待複審",IF(OR(AND(J21="需更正",K21=""),AND(J21="需更正",M21=""),AND(J21="需更正",N21=""),AND(J21="排除",OR(K21="",N21="")),AND(J21="需複審",P21="需更正",R21=""),AND(J21="需複審",P21="需更正",S21=""),AND(J21="需複審",P21="排除",S21="")),"錯誤：請補齊必填欄位","通過"))) -> 通過
... A52: TC00051 | B52: TC00051 | C52: 文化部臺灣手語語料庫 | D52: 自然環境 | E52: 臺灣的四季， | F52: 臺灣/四季 | G52: G2D4P1/a143｜篇章1段落1｜臺灣手語語料庫（測試版），文化部，https://tslcorpus.moc.gov.tw/ | H52: https://tslcorpus.moc.gov.tw/upload/24/web/video/GztyDxcEDJ2TtmIX.mp4 | I52: e3cad6494a6216c22906f8178456f348d908a8121add1f294bc27b60bf15eaab | J52: 通過 | O52: 否 | T52: =IF(J52="","未填",IF(J52="需複審",IF(OR(P52="",P52="仍需複審"),"待複審",P52),J52)) -> 通過 | U52: =IF(T52="通過",E52,IF(T52="需更正",IF(J52="需複審",IF(Q52="",E52,Q52),IF(L52="",E52,L52)),"")) -> 臺灣的四季， | V52: =IF(T52="通過",F52,IF(T52="需更正",IF(J52="需複審",R52,M52),"")) -> 臺灣/四季 | W52: =IF(AND(OR(T52="通過",AND(T52="需更正",V52<>"")),X52="通過"),"是","否") -> 是 | X52: =IF(J52="","未填",IF(AND(J52="需複審",OR(P52="",P52="仍需複審")),"待複審",IF(OR(AND(J52="需更正",K52=""),AND(J52="需更正",M52=""),AND(J52="需更正",N52=""),AND(J52="排除",OR(K52="",N52="")),AND(J52="需複審",P52="需更正",R52=""),AND(J52="需複審",P52="需更正",S52=""),AND(J52="需複審",P52="排除",S52="")),"錯誤：請補齊必填欄位","通過"))) -> 通過
A53: TC00052 | B53: TC00052 | C53: 文化部臺灣手語語料庫 | D53: 自然環境 | E53: 春天涼爽、夏季炎熱、秋天颳風、冬天寒冷。 | F53: 春季/涼爽/夏季/熱/秋季/風大/冬季/冷 | G53: G2D4P1/a932｜篇章1段落1｜臺灣手語語料庫（測試版），文化部，https://tslcorpus.moc.gov.tw/ | H53: https://tslcorpus.moc.gov.tw/upload/24/web/video/GztyDxcEDJ2TtmIX.mp4 | I53: d6a6c92afd28df74a864f23e20946814f48455adfb02ddf874748e6439cf0757 | J53: 需更正 | K53: 漏詞 | M53: 春季/涼爽/夏季/熱/秋季/風大/冬季/冷/有 | N53: 依文化部語料庫原始標註：補上「有」 | O53: 否 | T53: =IF(J53="","未填",IF(J53="需複審",IF(OR(P53="",P53="仍需複審"),"待複審",P53),J53)) -> 需更正 | U53: =IF(T53="通過",E53,IF(T53="需更正",IF(J53="需複審",IF(Q53="",E53,Q53),IF(L53="",E53,L53)),"")) -> 春天涼爽、夏季炎熱、秋天颳風、冬天寒冷。 | V53: =IF(T53="通過",F53,IF(T53="需更正",IF(J53="需複審",R53,M53),"")) -> 春季/涼爽/夏季/熱/秋季/風大/冬季/冷/有 | W53: =IF(AND(OR(T53="通過",AND(T53="需更正",V53<>"")),X53="通過"),"是","否") -> 是 | X53: =IF(J53="","未填",IF(AND(J53="需複審",OR(P53="",P53="仍需複審")),"待複審",IF(OR(AND(J53="需更正",K53=""),AND(J53="需更正",M53=""),AND(J53="需更正",N53=""),AND(J53="排除",OR(K53="",N53="")),AND(J53="需複審",P53="需更正",R53=""),AND(J53="需複審",P53="需更正",S53=""),AND(J53="需複審",P53="排除",S53="")),"錯誤：請補齊必填欄位","通過"))) -> 通過
A54: TC00053 | B54: TC00053 | C54: 文化部臺灣手語語料庫 | D54: 自然環境 | E54: 現在明明是冬季， 但早晚溫度差異大， | F54: 有/現在/冬季/對/但是/早上/熱+溫度上升/晚上/冷+溫度下降 | G54: G2D4P1/a144｜篇章1段落1｜臺灣手語語料庫（測試版），文化部，https://tslcorpus.moc.gov.tw/ | H54: https://tslcorpus.moc.gov.tw/upload/24/web/video/GztyDxcEDJ2TtmIX.mp4 | I54: e55223cabee153ad807fe18b60239943d78a963fb90e8d7213e0ec76d46502ef | J54: 需更正 | K54: 多餘詞 | M54: 現在/冬季/對/但是/早上/熱+溫度上升/晚上/冷+溫度下降 | N54: 依文化部語料庫原始標註：刪去「有」 | O54: 否 | T54: =IF(J54="","未填",IF(J54="需複審",IF(OR(P54="",P54="仍需複審"),"待複審",P54),J54)) -> 需更正 | U54: =IF(T54="通過",E54,IF(T54="需更正",IF(J54="需複審",IF(Q54="",E54,Q54),IF(L54="",E54,L54)),"")) -> 現在明明是冬季， 但早晚溫度差異大， | V54: =IF(T54="通過",F54,IF(T54="需更正",IF(J54="需複審",R54,M54),"")) -> 現在/冬季/對/但是/早上/熱+溫度上升/晚上/冷+溫度下降 | W54: =IF(AND(OR(T54="通過",AND(T54="需更正",V54<>"")),X54="通過"),"是","否") -> 是 | X54: =IF(J54="","未填",IF(AND(J54="需複審",OR(P54="",P54="仍需複審")),"待複審",IF(OR(AND(J54="需更正",K54=""),AND(J54="需更正",M54=""),AND(J54="需更正",N54=""),AND(J54="排除",OR(K54="",N54="")),AND(J54="需複審",P54="需更正",R54=""),AND(J54="需複審",P54="需更正",S54=""),AND(J54="需複審",P54="排除",S54="")),"錯誤：請補齊必填欄位","通過"))) -> 通過
A55: TC00054 | B55: TC00054 | C55: 文化部臺灣手語語料庫 | D55: 自然環境 | E55: 白天可高達30度， | F55: 白天/曬太陽/熱+溫度上升/三十度 | G55: G2D4P1/a145｜篇章1段落1｜臺灣手語語料庫（測試版），文化部，https://tslcorpus.moc.gov.tw/ | H55: https://tslcorpus.moc.gov.tw/upload/24/web/video/GztyDxcEDJ2TtmIX.mp4 | I55: 9d8a1eb746b3ae47fc37d097c2cc77527f7aa04564ab57fbd75d778b2eaad143 | J55: 通過 | O55: 否 | T55: =IF(J55="","未填",IF(J55="需複審",IF(OR(P55="",P55="仍需複審"),"待複審",P55),J55)) -> 通過 | U55: =IF(T55="通過",E55,IF(T55="需更正",IF(J55="需複審",IF(Q55="",E55,Q55),IF(L55="",E55,L55)),"")) -> 白天可高達30度， | V55: =IF(T55="通過",F55,IF(T55="需更正",IF(J55="需複審",R55,M55),"")) -> 白天/曬太陽/熱+溫度上升/三十度 | W55: =IF(AND(OR(T55="通過",AND(T55="需更正",V55<>"")),X55="通過"),"是","否") -> 是 | X55: =IF(J55="","未填",IF(AND(J55="需複審",OR(P55="",P55="仍需複審")),"待複審",IF(OR(AND(J55="需更正",K55=""),AND(J55="需更正",M55=""),AND(J55="需更正",N55=""),AND(J55="排除",OR(K55="",N55="")),AND(J55="需複審",P55="需更正",R55=""),AND(J55="需複審",P55="需更正",S55=""),AND(J55="需複審",P55="排除",S55="")),"錯誤：請補齊必填欄位","通過"))) -> 通過
A56: TC00055 | B56: TC00055 | C56: 文化部臺灣手語語料庫 | D56: 自然環境 | E56: 晚上也能冷到10度以下。 | F56: 晚上/冷+溫度下降/十+下 | G56: G2D4P1/a146｜篇章1段落1｜臺灣手語語料庫（測試版），文化部，https://tslcorpus.moc.gov.tw/ | H56: https://tslcorpus.moc.gov.tw/upload/24/web/video/GztyDxcEDJ2TtmIX.mp4 | I56: 81f01d0ee4b6a9a24420365bc283a10b23af7647ead7cc718645ff7bbba0983f | J56: 通過 | O56: 否 | T56: =IF(J56="","未填",IF(J56="需複審",IF(OR(P56="",P56="仍需複審"),"待複審",P56),J56)) -> 通過 | U56: =IF(T56="通過",E56,IF(T56="需更正",IF(J56="需複審",IF(Q56="",E56,Q56),IF(L56="",E56,L56)),"")) -> 晚上也能冷到10度以下。 | V56: =IF(T56="通過",F56,IF(T56="需更正",IF(J56="需複審",R56,M56),"")) -> 晚上/冷+溫度下降/十+下 | W56: =IF(AND(OR(T56="通過",AND(T56="需更正",V56<>"")),X56="通過"),"是","否") -> 是 | X56: =IF(J56="","未填",IF(AND(J56="需複審",OR(P56="",P56="仍需複審")),"待複審",IF(OR(AND(J56="需更正",K56=""),AND(J56="需更正",M56=""),AND(J56="需更正",N56=""),AND(J56="排除",OR(K56="",N56="")),AND(J56="需複審",P56="需更正",R56=""),AND(J56="需複審",P56="需更正",S56=""),AND(J56="需複審",P56="排除",S56="")),"錯誤：請補齊必填欄位","通過"))) -> 通過
A57: TC00056 | B57: TC00056 | C57: 文化部臺灣手語語料庫 | D57: 自然環境 | E57: 臺灣的地勢也很特別， | F57: 臺灣/地勢/特別/一樣 | G57: G2D4P1/a147｜篇章1段落1｜臺灣手語語料庫（測試版），文化部，https://tslcorpus.moc.gov.tw/ | H57: https://tslcorpus.moc.gov.tw/upload/24/web/video/GztyDxcEDJ2TtmIX.mp4 | I57: ab2fc9f22f62bf2494e2a05469db02dbecea9c2635c178f575026b2c5297c68f | J57: 通過 | O57: 否 | T57: =IF(J57="","未填",IF(J57="需複審",IF(OR(P57="",P57="仍需複審"),"待複審",P57),J57)) -> 通過 | U57: =IF(T57="通過",E57,IF(T57="需更正",IF(J57="需複審",IF(Q57="",E57,Q57),IF(L57="",E57,L57)),"")) -> 臺灣的地勢也很特別， | V57: =IF(T57="通過",F57,IF(T57="需更正",IF(J57="需複審",R57,M57),"")) -> 臺灣/地勢/特別/一樣 | W57: =IF(AND(OR(T57="通過",AND(T57="需更正",V57<>"")),X57="通過"),"是","否") -> 是 | X57: =IF(J57="","未填",IF(AND(J57="需複審",OR(P57="",P57="仍需複審")),"待複審",IF(OR(AND(J57="需更正",K57=""),AND(J57="需更正",M57=""),AND(J57="需更正",N57=""),AND(J57="排除",OR(K57="",N57="")),AND(J57="需複審",P57="需更正",R57=""),AND(J57="需複審",P57="需更正",S57=""),AND(J57="需複審",P57="排除",S57="")),"錯誤：請補齊必填欄位","通過"))) -> 通過
A58: TC00057 | B58: TC00057 | C58: 文化部臺灣手語語料庫 | D58: 自然環境 | E58: 有很多三千公尺以上的高山， | F58: 臺灣/這/山/高/公尺/三千+上/到處/多 | G58: G2D4P1/a148｜篇章1段落1｜臺灣手語語料庫（測試版），文化部，https://tslcorpus.moc.gov.tw/ | H58: https://tslcorpus.moc.gov.tw/upload/24/web/video/GztyDxcEDJ2TtmIX.mp4 | I58: 1b61c06e5b190a6d15a4ab12264019ed02c020a34f0266bae5bb2ffac22f557b | J58: 通過 | O58: 否 | T58: =IF(J58="","未填",IF(J58="需複審",IF(OR(P58="",P58="仍需複審"),"待複審",P58),J58)) -> 通過 | U58: =IF(T58="通過",E58,IF(T58="需更正",IF(J58="需複審",IF(Q58="",E58,Q58),IF(L58="",E58,L58)),"")) -> 有很多三千公尺以上的高山， | V58: =IF(T58="通過",F58,IF(T58="需更正",IF(J58="需複審",R58,M58),"")) -> 臺灣/這/山/高/公尺/三千+上/到處/多 | W58: =IF(AND(OR(T58="通過",AND(T58="需更正",V58<>"")),X58="通過"),"是","否") -> 是 | X58: =IF(J58="","未填",IF(AND(J58="需複審",OR(P58="",P58="仍需複審")),"待複審",IF(OR(AND(J58="需更正",K58=""),AND(J58="需更正",M58=""),AND(J58="需更正",N58=""),AND(J58="排除",OR(K58="",N58="")),AND(J58="需複審",P58="需更正",R58=""),AND(J58="需複審",P58="需更正",S58=""),AND(J58="需複審",P58="排除",S58="")),"錯誤：請補齊必填欄位","通過"))) -> 通過
A59: TC00058 | B59: TC00058 | C59: 文化部臺灣手語語料庫 | D59: 自然環境 | E59: 還有那美麗蜿蜒崎嶇的海岸線。 | F59: 再/海岸/蜿蜒/看 | G59: G2D4P1/a149｜篇章1段落1｜臺灣手語語料庫（測試版），文化部，https://tslcorpus.moc.gov.tw/ | H59: https://tslcorpus.moc.gov.tw/upload/24/web/video/GztyDxcEDJ2TtmIX.mp4 | I59: 7f7e15026f5d3d58590d801fee19bfc4f531398a48670cb58d2dd9bc7ab55d79 | J59: 需更正 | K59: 漏詞 | M59: 再/海岸/蜿蜒/看/漂亮 | N59: 漏詞 | O59: 否 | T59: =IF(J59="","未填",IF(J59="需複審",IF(OR(P59="",P59="仍需複審"),"待複審",P59),J59)) -> 需更正 | U59: =IF(T59="通過",E59,IF(T59="需更正",IF(J59="需複審",IF(Q59="",E59,Q59),IF(L59="",E59,L59)),"")) -> 還有那美麗蜿蜒崎嶇的海岸線。 | V59: =IF(T59="通過",F59,IF(T59="需更正",IF(J59="需複審",R59,M59),"")) -> 再/海岸/蜿蜒/看/漂亮 | W59: =IF(AND(OR(T59="通過",AND(T59="需更正",V59<>"")),X59="通過"),"是","否") -> 是 | X59: =IF(J59="","未填",IF(AND(J59="需複審",OR(P59="",P59="仍需複審")),"待複審",IF(OR(AND(J59="需更正",K59=""),AND(J59="需更正",M59=""),AND(J59="需更正",N59=""),AND(J59="排除",OR(K59="",N59="")),AND(J59="需複審",P59="需更正",R59=""),AND(J59="需複審",P59="需更正",S59=""),AND(J59="需複審",P59="排除",S59="")),"錯誤：請補齊必填欄位","通過"))) -> 通過
A60: TC00059 | B60: TC00059 | C60: 文化部臺灣手語語料庫 | D60: 自然環境 | E60: 如果想要爬山， | F60: 漂亮/如果/去/登山/要 | G60: G2D4P1/a150｜篇章1段落1｜臺灣手語語料庫（測試版），文化部，https://tslcorpus.moc.gov.tw/ | H60: https://tslcorpus.moc.gov.tw/upload/24/web/video/GztyDxcEDJ2TtmIX.mp4 | I60: 96da4dbcaebc960076532a725729ddac3a75105ec6cead8ad4eec57c37c538e6 | J60: 需更正 | K60: 多餘詞 | M60: 如果/去/登山/要 | N60: 多餘詞 | O60: 否 | T60: =IF(J60="","未填",IF(J60="需複審",IF(OR(P60="",P60="仍需複審"),"待複審",P60),J60)) -> 需更正 | U60: =IF(T60="通過",E60,IF(T60="需更正",IF(J60="需複審",IF(Q60="",E60,Q60),IF(L60="",E60,L60)),"")) -> 如果想要爬山， | V60: =IF(T60="通過",F60,IF(T60="需更正",IF(J60="需複審",R60,M60),"")) -> 如果/去/登山/要 | W60: =IF(AND(OR(T60="通過",AND(T60="需更正",V60<>"")),X60="通過"),"是","否") -> 是 | X60: =IF(J60="","未填",IF(AND(J60="需複審",OR(P60="",P60="仍需複審")),"待複審",IF(OR(AND(J60="需更正",K60=""),AND(J60="需更正",M60=""),AND(J60="需更正",N60=""),AND(J60="排除",OR(K60="",N60="")),AND(J60="需複審",P60="需更正",R60=""),AND(J60="需複審",P60="需更正",S60=""),AND(J60="需複審",P60="排除",S60="")),"錯誤：請補齊必填欄位","通過"))) -> 通過
A61: TC00060 | B61: TC00060 | C61: 文化部臺灣手語語料庫 | D61: 自然環境 | E61: 驅車前往三、四個小時一下子就到； | F61: 車子/開車/三小時/四小時 | G61: G2D4P1/a151｜篇章1段落1｜臺灣手語語料庫（測試版），文化部，https://tslcorpus.moc.gov.tw/ | H61: https://tslcorpus.moc.gov.tw/upload/24/web/video/GztyDxcEDJ2TtmIX.mp4 | I61: 6c1e50e8b75ebf0ac266151c89bbd11fd7eb010510d958b4aa8b97edfdb016b5 | J61: 需更正 | K61: 漏詞 | M61: 車子/開車/三小時/四小時/一下子 | N61: 漏詞 | O61: 否 | T61: =IF(J61="","未填",IF(J61="需複審",IF(OR(P61="",P61="仍需複審"),"待複審",P61),J61)) -> 需更正 | U61: =IF(T61="通過",E61,IF(T61="需更正",IF(J61="需複審",IF(Q61="",E61,Q61),IF(L61="",E61,L61)),"")) -> 驅車前往三、四個小時一下子就到； | V61: =IF(T61="通過",F61,IF(T61="需更正",IF(J61="需複審",R61,M61),"")) -> 車子/開車/三小時/四小時/一下子 | W61: =IF(AND(OR(T61="通過",AND(T61="需更正",V61<>"")),X61="通過"),"是","否") -> 是 | X61: =IF(J61="","未填",IF(AND(J61="需複審",OR(P61="",P61="仍需複審")),"待複審",IF(OR(AND(J61="需更正",K61=""),AND(J61="需更正",M61=""),AND(J61="需更正",N61=""),AND(J61="排除",OR(K61="",N61="")),AND(J61="需複審",P61="需更正",R61=""),AND(J61="需複審",P61="需更正",S61=""),AND(J61="需複審",P61="排除",S61="")),"錯誤：請補齊必填欄位","通過"))) -> 通過
A62: TC00061 | B62: TC00061 | C62: 文化部臺灣手語語料庫 | D62: 自然環境 | E62: 如果想要去海邊游泳， | F62: 一下子/如果/去/海邊/海邊+游泳/要 | G62: G2D4P1/a152｜篇章1段落1｜臺灣手語語料庫（測試版），文化部，https://tslcorpus.moc.gov.tw/ | H62: https://tslcorpus.moc.gov.tw/upload/24/web/video/GztyDxcEDJ2TtmIX.mp4 | I62: a2dccd74e107509f990bf801117556f411a6d88de3b8f2968819cf3baf69a2a8 | J62: 需更正 | K62: 多餘詞 | M62: 如果/去/海邊/海邊+游泳/要 | N62: 多餘詞 | O62: 否 | T62: =IF(J62="","未填",IF(J62="需複審",IF(OR(P62="",P62="仍需複審"),"待複審",P62),J62)) -> 需更正 | U62: =IF(T62="通過",E62,IF(T62="需更正",IF(J62="需複審",IF(Q62="",E62,Q62),IF(L62="",E62,L62)),"")) -> 如果想要去海邊游泳， | V62: =IF(T62="通過",F62,IF(T62="需更正",IF(J62="需複審",R62,M62),"")) -> 如果/去/海邊/海邊+游泳/要 | W62: =IF(AND(OR(T62="通過",AND(T62="需更正",V62<>"")),X62="通過"),"是","否") -> 是 | X62: =IF(J62="","未填",IF(AND(J62="需複審",OR(P62="",P62="仍需複審")),"待複審",IF(OR(AND(J62="需更正",K62=""),AND(J62="需更正",M62=""),AND(J62="需更正",N62=""),AND(J62="排除",OR(K62="",N62="")),AND(J62="需複審",P62="需更正",R62=""),AND(J62="需複審",P62="需更正",S62=""),AND(J62="需複審",P62="排除",S62="")),"錯誤：請補齊必填欄位","通過"))) -> 通過
A63: TC00062 | B63: TC00062 | C63: 文化部臺灣手語語料庫 | D63: 自然環境 | E63: 也是一下子就到了。 | F63: 去/一下子 | G63: G2D4P1/a153｜篇章1段落1｜臺灣手語語料庫（測試版），文化部，https://tslcorpus.moc.gov.tw/ | H63: https://tslcorpus.moc.gov.tw/upload/24/web/video/GztyDxcEDJ2TtmIX.mp4 | I63: 990c41990a499ef6a020511860ee4796e32c297ba33d7000f70c5d3b2487fae9 | J63: 需更正 | K63: 漏詞 | M63: 去/一下子/一樣 | N63: 漏詞 | O63: 否 | T63: =IF(J63="","未填",IF(J63="需複審",IF(OR(P63="",P63="仍需複審"),"待複審",P63),J63)) -> 需更正 | U63: =IF(T63="通過",E63,IF(T63="需更正",IF(J63="需複審",IF(Q63="",E63,Q63),IF(L63="",E63,L63)),"")) -> 也是一下子就到了。 | V63: =IF(T63="通過",F63,IF(T63="需更正",IF(J63="需複審",R63,M63),"")) -> 去/一下子/一樣 | W63: =IF(AND(OR(T63="通過",AND(T63="需更正",V63<>"")),X63="通過"),"是","否") -> 是 | X63: =IF(J63="","未填",IF(AND(J63="需複審",OR(P63="",P63="仍需複審")),"待複審",IF(OR(AND(J63="需更正",K63=""),AND(J63="需更正",M63=""),AND(J63="需更正",N63=""),AND(J63="排除",OR(K63="",N63="")),AND(J63="需複審",P63="需更正",R63=""),AND(J63="需複審",P63="需更正",S63=""),AND(J63="需複審",P63="排除",S63="")),"錯誤：請補齊必填欄位","通過"))) -> 通過
A64: TC00063 | B64: TC00063 | C64: 文化部臺灣手語語料庫 | D64: 自然環境 | E64: 有可能早上去登山完， | F64: 一樣/可能/早上/去/登山/完 | G64: G2D4P1/a154｜篇章1段落1｜臺灣手語語料庫（測試版），文化部，https://tslcorpus.moc.gov.tw/ | H64: https://tslcorpus.moc.gov.tw/upload/24/web/video/GztyDxcEDJ2TtmIX.mp4 | I64: 1c6d8de6c44d0acddba8080d4455497577f02f14d09d2b56a51adad4b4db0e9a | J64: 需更正 | K64: 多餘詞 | M64: 可能/早上/去/登山/完 | N64: 多餘詞 | O64: 否 | T64: =IF(J64="","未填",IF(J64="需複審",IF(OR(P64="",P64="仍需複審"),"待複審",P64),J64)) -> 需更正 | U64: =IF(T64="通過",E64,IF(T64="需更正",IF(J64="需複審",IF(Q64="",E64,Q64),IF(L64="",E64,L64)),"")) -> 有可能早上去登山完， | V64: =IF(T64="通過",F64,IF(T64="需更正",IF(J64="需複審",R64,M64),"")) -> 可能/早上/去/登山/完 | W64: =IF(AND(OR(T64="通過",AND(T64="需更正",V64<>"")),X64="通過"),"是","否") -> 是 | X64: =IF(J64="","未填",IF(AND(J64="需複審",OR(P64="",P64="仍需複審")),"待複審",IF(OR(AND(J64="需更正",K64=""),AND(J64="需更正",M64=""),AND(J64="需更正",N64=""),AND(J64="排除",OR(K64="",N64="")),AND(J64="需複審",P64="需更正",R64=""),AND(J64="需複審",P64="需更正",S64=""),AND(J64="需複審",P64="排除",S64="")),"錯誤：請補齊必填欄位","通過"))) -> 通過
A65: TC00064 | B65: TC00064 | C65: 文化部臺灣手語語料庫 | D65: 自然環境 | E65: 下午就去海邊自由自在的游泳。 | F65: 下午/去/海邊/海邊+游泳/自由/悠閒 | G65: G2D4P1/a155｜篇章1段落1｜臺灣手語語料庫（測試版），文化部，https://tslcorpus.moc.gov.tw/ | H65: https://tslcorpus.moc.gov.tw/upload/24/web/video/GztyDxcEDJ2TtmIX.mp4 | I65: 2def2aa277c130d5524564d2db49e691b8ed184daed3e0ef9b18dea9365e8b93 | J65: 通過 | O65: 否 | T65: =IF(J65="","未填",IF(J65="需複審",IF(OR(P65="",P65="仍需複審"),"待複審",P65),J65)) -> 通過 | U65: =IF(T65="通過",E65,IF(T65="需更正",IF(J65="需複審",IF(Q65="",E65,Q65),IF(L65="",E65,L65)),"")) -> 下午就去海邊自由自在的游泳。 | V65: =IF(T65="通過",F65,IF(T65="需更正",IF(J65="需複審",R65,M65),"")) -> 下午/去/海邊/海邊+游泳/自由/悠閒 | W65: =IF(AND(OR(T65="通過",AND(T65="需更正",V65<>"")),X65="通過"),"是","否") -> 是 | X65: =IF(J65="","未填",IF(AND(J65="需複審",OR(P65="",P65="仍需複審")),"待複審",IF(OR(AND(J65="需更正",K65=""),AND(J65="需更正",M65=""),AND(J65="需更正",N65=""),AND(J65="排除",OR(K65="",N65="")),AND(J65="需複審",P65="需更正",R65=""),AND(J65="需複審",P65="需更正",S65=""),AND(J65="需複審",P65="排除",S65="")),"錯誤：請補齊必填欄位","通過"))) -> 通過
A66: TC00065 | B66: TC00065 | C66: 文化部臺灣手語語料庫 | D66: 日常起居 | E66: 我老家在台中， | F66: 我/老家/臺中 | G66: G4D2P1/a139｜篇章1段落1｜臺灣手語語料庫（測試版），文化部，https://tslcorpus.moc.gov.tw/ | H66: https://tslcorpus.moc.gov.tw/upload/24/web/video/LJhgFLDWoNQPbQHZ.mp4 | I66: dc92d6421de0ffb80a51dba9972c9ed69d56fc0faafa62e56c04d0724c1764ba | J66: 通過 | O66: 否 | T66: =IF(J66="","未填",IF(J66="需複審",IF(OR(P66="",P66="仍需複審"),"待複審",P66),J66)) -> 通過 | U66: =IF(T66="通過",E66,IF(T66="需更正",IF(J66="需複審",IF(Q66="",E66,Q66),IF(L66="",E66,L66)),"")) -> 我老家在台中， | V66: =IF(T66="通過",F66,IF(T66="需更正",IF(J66="需複審",R66,M66),"")) -> 我/老家/臺中 | W66: =IF(AND(OR(T66="通過",AND(T66="需更正",V66<>"")),X66="通過"),"是","否") -> 是 | X66: =IF(J66="","未填",IF(AND(J66="需複審",OR(P66="",P66="仍需複審")),"待複審",IF(OR(AND(J66="需更正",K66=""),AND(J66="需更正",M66=""),AND(J66="需更正",N66=""),AND(J66="排除",OR(K66="",N66="")),AND(J66="需複審",P66="需更正",R66=""),AND(J66="需複審",P66="需更正",S66=""),AND(J66="需複審",P66="排除",S66="")),"錯誤：請補齊必填欄位","通過"))) -> 通過
A67: TC00066 | B67: TC00066 | C67: 文化部臺灣手語語料庫 | D67: 日常起居 | E67: 嫁到雲林後懷孕， | F67: 嫁過去/雲林/之後/懷孕 | G67: G4D2P1/a140｜篇章1段落1｜臺灣手語語料庫（測試版），文化部，https://tslcorpus.moc.gov.tw/ | H67: https://tslcorpus.moc.gov.tw/upload/24/web/video/LJhgFLDWoNQPbQHZ.mp4 | I67: a78459394dcbdb81c5c419ee281180bb70db4839fdfdcbb7e526612e06fa9728 | J67: 通過 | O67: 否 | T67: =IF(J67="","未填",IF(J67="需複審",IF(OR(P67="",P67="仍需複審"),"待複審",P67),J67)) -> 通過 | U67: =IF(T67="通過",E67,IF(T67="需更正",IF(J67="需複審",IF(Q67="",E67,Q67),IF(L67="",E67,L67)),"")) -> 嫁到雲林後懷孕， | V67: =IF(T67="通過",F67,IF(T67="需更正",IF(J67="需複審",R67,M67),"")) -> 嫁過去/雲林/之後/懷孕 | W67: =IF(AND(OR(T67="通過",AND(T67="需更正",V67<>"")),X67="通過"),"是","否") -> 是 | X67: =IF(J67="","未填",IF(AND(J67="需複審",OR(P67="",P67="仍需複審")),"待複審",IF(OR(AND(J67="需更正",K67=""),AND(J67="需更正",M67=""),AND(J67="需更正",N67=""),AND(J67="排除",OR(K67="",N67="")),AND(J67="需複審",P67="需更正",R67=""),AND(J67="需複審",P67="需更正",S67=""),AND(J67="需複審",P67="排除",S67="")),"錯誤：請補齊必填欄位","通過"))) -> 通過
A68: TC00067 | B68: TC00067 | C68: 文化部臺灣手語語料庫 | D68: 日常起居 | E68: 接著小孩出生要照顧小孩， | F68: 小孩/出生/照顧 | G68: G4D2P1/a141｜篇章1段落1｜臺灣手語語料庫（測試版），文化部，https://tslcorpus.moc.gov.tw/ | H68: https://tslcorpus.moc.gov.tw/upload/24/web/video/LJhgFLDWoNQPbQHZ.mp4 | I68: 0be7baade92d57fe2d37e1d9f6968d6160d013421bdfadd496aa76423383e330 | J68: 通過 | O68: 否 | T68: =IF(J68="","未填",IF(J68="需複審",IF(OR(P68="",P68="仍需複審"),"待複審",P68),J68)) -> 通過 | U68: =IF(T68="通過",E68,IF(T68="需更正",IF(J68="需複審",IF(Q68="",E68,Q68),IF(L68="",E68,L68)),"")) -> 接著小孩出生要照顧小孩， | V68: =IF(T68="通過",F68,IF(T68="需更正",IF(J68="需複審",R68,M68),"")) -> 小孩/出生/照顧 | W68: =IF(AND(OR(T68="通過",AND(T68="需更正",V68<>"")),X68="通過"),"是","否") -> 是 | X68: =IF(J68="","未填",IF(AND(J68="需複審",OR(P68="",P68="仍需複審")),"待複審",IF(OR(AND(J68="需更正",K68=""),AND(J68="需更正",M68=""),AND(J68="需更正",N68=""),AND(J68="排除",OR(K68="",N68="")),AND(J68="需複審",P68="需更正",R68=""),AND(J68="需複審",P68="需更正",S68=""),AND(J68="需複審",P68="排除",S68="")),"錯誤：請補齊必填欄位","通過"))) -> 通過
A69: TC00068 | B69: TC00068 | C69: 文化部臺灣手語語料庫 | D69: 日常起居 | E69: 所以沒辦法工作， | F69: 工作 | G69: G4D2P1/a142｜篇章1段落1｜臺灣手語語料庫（測試版），文化部，https://tslcorpus.moc.gov.tw/ | H69: https://tslcorpus.moc.gov.tw/upload/24/web/video/LJhgFLDWoNQPbQHZ.mp4 | I69: 5818d19448ad5eb53e403ad94320f465e6bdaf2b397aa1dfdf45b70b2cb197f9 | J69: 需更正 | K69: 漏詞 | M69: 工作/沒辦法 | N69: 漏詞 | O69: 否 | T69: =IF(J69="","未填",IF(J69="需複審",IF(OR(P69="",P69="仍需複審"),"待複審",P69),J69)) -> 需更正 | U69: =IF(T69="通過",E69,IF(T69="需更正",IF(J69="需複審",IF(Q69="",E69,Q69),IF(L69="",E69,L69)),"")) -> 所以沒辦法工作， | V69: =IF(T69="通過",F69,IF(T69="需更正",IF(J69="需複審",R69,M69),"")) -> 工作/沒辦法 | W69: =IF(AND(OR(T69="通過",AND(T69="需更正",V69<>"")),X69="通過"),"是","否") -> 是 | X69: =IF(J69="","未填",IF(AND(J69="需複審",OR(P69="",P69="仍需複審")),"待複審",IF(OR(AND(J69="需更正",K69=""),AND(J69="需更正",M69=""),AND(J69="需更正",N69=""),AND(J69="排除",OR(K69="",N69="")),AND(J69="需複審",P69="需更正",R69=""),AND(J69="需複審",P69="需更正",S69=""),AND(J69="需複審",P69="排除",S69="")),"錯誤：請補齊必填欄位","通過"))) -> 通過
A70: TC00069 | B70: TC00069 | C70: 文化部臺灣手語語料庫 | D70: 日常起居 | E70: 等小孩三歲上幼兒園才開始找工作。 | F70: 沒辦法/等/小孩/長大/三歲/幼兒園/丟/之後/工作/找 | G70: G4D2P1/a143｜篇章1段落1｜臺灣手語語料庫（測試版），文化部，https://tslcorpus.moc.gov.tw/ | H70: https://tslcorpus.moc.gov.tw/upload/24/web/video/LJhgFLDWoNQPbQHZ.mp4 | I70: cf241d5b96e0b56fbe3129f71ebeea737d28155898531f9de8740ac62f4ee928 | J70: 需更正 | K70: 多餘詞 | M70: 等/小孩/長大/三歲/幼兒園/丟/之後/工作/找 | N70: 多餘詞 | O70: 否 | T70: =IF(J70="","未填",IF(J70="需複審",IF(OR(P70="",P70="仍需複審"),"待複審",P70),J70)) -> 需更正 | U70: =IF(T70="通過",E70,IF(T70="需更正",IF(J70="需複審",IF(Q70="",E70,Q70),IF(L70="",E70,L70)),"")) -> 等小孩三歲上幼兒園才開始找工作。 | V70: =IF(T70="通過",F70,IF(T70="需更正",IF(J70="需複審",R70,M70),"")) -> 等/小孩/長大/三歲/幼兒園/丟/之後/工作/找 | W70: =IF(AND(OR(T70="通過",AND(T70="需更正",V70<>"")),X70="通過"),"是","否") -> 是 | X70: =IF(J70="","未填",IF(AND(J70="需複審",OR(P70="",P70="仍需複審")),"待複審",IF(OR(AND(J70="需更正",K70=""),AND(J70="需更正",M70=""),AND(J70="需更正",N70=""),AND(J70="排除",OR(K70="",N70="")),AND(J70="需複審",P70="需更正",R70=""),AND(J70="需複審",P70="需更正",S70=""),AND(J70="需複審",P70="排除",S70="")),"錯誤：請補齊必填欄位","通過"))) -> 通過
A71: TC00070 | B71: TC00070 | C71: 文化部臺灣手語語料庫 | D71: 日常起居 | E71: 有朋友告訴我說有聾人清潔隊， | F71: 朋友/告訴/聾人/清潔隊/有 | G71: G4D2P1/a144｜篇章1段落1｜臺灣手語語料庫（測試版），文化部，https://tslcorpus.moc.gov.tw/ | H71: https://tslcorpus.moc.gov.tw/upload/24/web/video/LJhgFLDWoNQPbQHZ.mp4 | I71: 4a43c9e96a685763bad72a12bf64d171a43b5def8e90dc8105a70072d0756e2f | J71: 通過 | O71: 否 | T71: =IF(J71="","未填",IF(J71="需複審",IF(OR(P71="",P71="仍需複審"),"待複審",P71),J71)) -> 通過 | U71: =IF(T71="通過",E71,IF(T71="需更正",IF(J71="需複審",IF(Q71="",E71,Q71),IF(L71="",E71,L71)),"")) -> 有朋友告訴我說有聾人清潔隊， | V71: =IF(T71="通過",F71,IF(T71="需更正",IF(J71="需複審",R71,M71),"")) -> 朋友/告訴/聾人/清潔隊/有 | W71: =IF(AND(OR(T71="通過",AND(T71="需更正",V71<>"")),X71="通過"),"是","否") -> 是 | X71: =IF(J71="","未填",IF(AND(J71="需複審",OR(P71="",P71="仍需複審")),"待複審",IF(OR(AND(J71="需更正",K71=""),AND(J71="需更正",M71=""),AND(J71="需更正",N71=""),AND(J71="排除",OR(K71="",N71="")),AND(J71="需複審",P71="需更正",R71=""),AND(J71="需複審",P71="需更正",S71=""),AND(J71="需複審",P71="排除",S71="")),"錯誤：請補齊必填欄位","通過"))) -> 通過
A72: TC00071 | B72: TC00071 | C72: 文化部臺灣手語語料庫 | D72: 日常起居 | E72: 福利還不錯， | F72: 福利/不錯 | G72: G4D2P1/a145｜篇章1段落1｜臺灣手語語料庫（測試版），文化部，https://tslcorpus.moc.gov.tw/ | H72: https://tslcorpus.moc.gov.tw/upload/24/web/video/LJhgFLDWoNQPbQHZ.mp4 | I72: 2c433d50fad962d49d0492bb1dfde864344962c984885e75abf80bc91311075e | J72: 通過 | O72: 否 | T72: =IF(J72="","未填",IF(J72="需複審",IF(OR(P72="",P72="仍需複審"),"待複審",P72),J72)) -> 通過 | U72: =IF(T72="通過",E72,IF(T72="需更正",IF(J72="需複審",IF(Q72="",E72,Q72),IF(L72="",E72,L72)),"")) -> 福利還不錯， | V72: =IF(T72="通過",F72,IF(T72="需更正",IF(J72="需複審",R72,M72),"")) -> 福利/不錯 | W72: =IF(AND(OR(T72="通過",AND(T72="需更正",V72<>"")),X72="通過"),"是","否") -> 是 | X72: =IF(J72="","未填",IF(AND(J72="需複審",OR(P72="",P72="仍需複審")),"待複審",IF(OR(AND(J72="需更正",K72=""),AND(J72="需更正",M72=""),AND(J72="需更正",N72=""),AND(J72="排除",OR(K72="",N72="")),AND(J72="需複審",P72="需更正",R72=""),AND(J72="需複審",P72="需更正",S72=""),AND(J72="需複審",P72="排除",S72="")),"錯誤：請補齊必填欄位","通過"))) -> 通過
A73: TC00072 | B73: TC00072 | C73: 文化部臺灣手語語料庫 | D73: 日常起居 | E73: 所以我就加入了。 | F73: 我/進入 | G73: G4D2P1/a146｜篇章1段落1｜臺灣手語語料庫（測試版），文化部，https://tslcorpus.moc.gov.tw/ | H73: https://tslcorpus.moc.gov.tw/upload/24/web/video/LJhgFLDWoNQPbQHZ.mp4 | I73: be7d2f0673867809c5ad36b622faecd1bb8eac2841ce8f11729f1ff00478ea64 | J73: 通過 | O73: 否 | T73: =IF(J73="","未填",IF(J73="需複審",IF(OR(P73="",P73="仍需複審"),"待複審",P73),J73)) -> 通過 | U73: =IF(T73="通過",E73,IF(T73="需更正",IF(J73="需複審",IF(Q73="",E73,Q73),IF(L73="",E73,L73)),"")) -> 所以我就加入了。 | V73: =IF(T73="通過",F73,IF(T73="需更正",IF(J73="需複審",R73,M73),"")) -> 我/進入 | W73: =IF(AND(OR(T73="通過",AND(T73="需更正",V73<>"")),X73="通過"),"是","否") -> 是 | X73: =IF(J73="","未填",IF(AND(J73="需複審",OR(P73="",P73="仍需複審")),"待複審",IF(OR(AND(J73="需更正",K73=""),AND(J73="需更正",M73=""),AND(J73="需更正",N73=""),AND(J73="排除",OR(K73="",N73="")),AND(J73="需複審",P73="需更正",R73=""),AND(J73="需複審",P73="需更正",S73=""),AND(J73="需複審",P73="排除",S73="")),"錯誤：請補齊必填欄位","通過"))) -> 通過
A74: TC00073 | B74: TC00073 | C74: 文化部臺灣手語語料庫 | D74: 日常起居 | E74: 剛開始什麼都不會， | F74: 首次/工作/情形/任何/不懂 | G74: G4D2P1/a147｜篇章1段落1｜臺灣手語語料庫（測試版），文化部，https://tslcorpus.moc.gov.tw/ | H74: https://tslcorpus.moc.gov.tw/upload/24/web/video/LJhgFLDWoNQPbQHZ.mp4 | I74: 8349bf63a14f3e9a63de856081cc6ffc5a2b9dfb24edefb44c86ebd924e6cd60 | J74: 通過 | O74: 否 | T74: =IF(J74="","未填",IF(J74="需複審",IF(OR(P74="",P74="仍需複審"),"待複審",P74),J74)) -> 通過 | U74: =IF(T74="通過",E74,IF(T74="需更正",IF(J74="需複審",IF(Q74="",E74,Q74),IF(L74="",E74,L74)),"")) -> 剛開始什麼都不會， | V74: =IF(T74="通過",F74,IF(T74="需更正",IF(J74="需複審",R74,M74),"")) -> 首次/工作/情形/任何/不懂 | W74: =IF(AND(OR(T74="通過",AND(T74="需更正",V74<>"")),X74="通過"),"是","否") -> 是 | X74: =IF(J74="","未填",IF(AND(J74="需複審",OR(P74="",P74="仍需複審")),"待複審",IF(OR(AND(J74="需更正",K74=""),AND(J74="需更正",M74=""),AND(J74="需更正",N74=""),AND(J74="排除",OR(K74="",N74="")),AND(J74="需複審",P74="需更正",R74=""),AND(J74="需複審",P74="需更正",S74=""),AND(J74="需複審",P74="排除",S74="")),"錯誤：請補齊必填欄位","通過"))) -> 通過
A75: TC00074 | B75: TC00074 | C75: 文化部臺灣手語語料庫 | D75: 日常起居 | E75: 聾人同事先教我三項工作技巧， | F75: 聾人/技巧/教/有三個 | G75: G4D2P1/a148｜篇章1段落1｜臺灣手語語料庫（測試版），文化部，https://tslcorpus.moc.gov.tw/ | H75: https://tslcorpus.moc.gov.tw/upload/24/web/video/LJhgFLDWoNQPbQHZ.mp4 | I75: a8968ecaf663c851bddeef0b0cf1892b4fe363c7314b3cc5756fec6e486f3a99 | J75: 通過 | O75: 否 | T75: =IF(J75="","未填",IF(J75="需複審",IF(OR(P75="",P75="仍需複審"),"待複審",P75),J75)) -> 通過 | U75: =IF(T75="通過",E75,IF(T75="需更正",IF(J75="需複審",IF(Q75="",E75,Q75),IF(L75="",E75,L75)),"")) -> 聾人同事先教我三項工作技巧， | V75: =IF(T75="通過",F75,IF(T75="需更正",IF(J75="需複審",R75,M75),"")) -> 聾人/技巧/教/有三個 | W75: =IF(AND(OR(T75="通過",AND(T75="需更正",V75<>"")),X75="通過"),"是","否") -> 是 | X75: =IF(J75="","未填",IF(AND(J75="需複審",OR(P75="",P75="仍需複審")),"待複審",IF(OR(AND(J75="需更正",K75=""),AND(J75="需更正",M75=""),AND(J75="需更正",N75=""),AND(J75="排除",OR(K75="",N75="")),AND(J75="需複審",P75="需更正",R75=""),AND(J75="需複審",P75="需更正",S75=""),AND(J75="需複審",P75="排除",S75="")),"錯誤：請補齊必填欄位","通過"))) -> 通過
A76: TC00075 | B76: TC00075 | C76: 文化部臺灣手語語料庫 | D76: 日常起居 | E76: 首先清潔窗戶要先準備兩條抹布， | F76: 第一/窗戶/清潔/技巧/抹布/準備/一共二個 | G76: G4D2P1/a149｜篇章1段落1｜臺灣手語語料庫（測試版），文化部，https://tslcorpus.moc.gov.tw/ | H76: https://tslcorpus.moc.gov.tw/upload/24/web/video/LJhgFLDWoNQPbQHZ.mp4 | I76: 0543f26de08acd8545aadbe4ba86ab5928cecddaf24ae8e7876b93ae2e27f20f | J76: 通過 | O76: 否 | T76: =IF(J76="","未填",IF(J76="需複審",IF(OR(P76="",P76="仍需複審"),"待複審",P76),J76)) -> 通過 | U76: =IF(T76="通過",E76,IF(T76="需更正",IF(J76="需複審",IF(Q76="",E76,Q76),IF(L76="",E76,L76)),"")) -> 首先清潔窗戶要先準備兩條抹布， | V76: =IF(T76="通過",F76,IF(T76="需更正",IF(J76="需複審",R76,M76),"")) -> 第一/窗戶/清潔/技巧/抹布/準備/一共二個 | W76: =IF(AND(OR(T76="通過",AND(T76="需更正",V76<>"")),X76="通過"),"是","否") -> 是 | X76: =IF(J76="","未填",IF(AND(J76="需複審",OR(P76="",P76="仍需複審")),"待複審",IF(OR(AND(J76="需更正",K76=""),AND(J76="需更正",M76=""),AND(J76="需更正",N76=""),AND(J76="排除",OR(K76="",N76="")),AND(J76="需複審",P76="需更正",R76=""),AND(J76="需複審",P76="需更正",S76=""),AND(J76="需複審",P76="排除",S76="")),"錯誤：請補齊必填欄位","通過"))) -> 通過
A77: TC00076 | B77: TC00076 | C77: 文化部臺灣手語語料庫 | D77: 日常起居 | E77: 一條乾的， | F77: 乾/一 | G77: G4D2P1/a150｜篇章1段落1｜臺灣手語語料庫（測試版），文化部，https://tslcorpus.moc.gov.tw/ | H77: https://tslcorpus.moc.gov.tw/upload/24/web/video/LJhgFLDWoNQPbQHZ.mp4 | I77: afebd75565fdc2016f705d32050ca99571e48c864a792eab219fa362485823bb | J77: 通過 | O77: 否 | T77: =IF(J77="","未填",IF(J77="需複審",IF(OR(P77="",P77="仍需複審"),"待複審",P77),J77)) -> 通過 | U77: =IF(T77="通過",E77,IF(T77="需更正",IF(J77="需複審",IF(Q77="",E77,Q77),IF(L77="",E77,L77)),"")) -> 一條乾的， | V77: =IF(T77="通過",F77,IF(T77="需更正",IF(J77="需複審",R77,M77),"")) -> 乾/一 | W77: =IF(AND(OR(T77="通過",AND(T77="需更正",V77<>"")),X77="通過"),"是","否") -> 是 | X77: =IF(J77="","未填",IF(AND(J77="需複審",OR(P77="",P77="仍需複審")),"待複審",IF(OR(AND(J77="需更正",K77=""),AND(J77="需更正",M77=""),AND(J77="需更正",N77=""),AND(J77="排除",OR(K77="",N77="")),AND(J77="需複審",P77="需更正",R77=""),AND(J77="需複審",P77="需更正",S77=""),AND(J77="需複審",P77="排除",S77="")),"錯誤：請補齊必填欄位","通過"))) -> 通過
A78: TC00077 | B78: TC00077 | C78: 文化部臺灣手語語料庫 | D78: 日常起居 | E78: 一張濕的， | F78: 水/一 | G78: G4D2P1/a913｜篇章1段落1｜臺灣手語語料庫（測試版），文化部，https://tslcorpus.moc.gov.tw/ | H78: https://tslcorpus.moc.gov.tw/upload/24/web/video/LJhgFLDWoNQPbQHZ.mp4 | I78: e9fb7c8552ad68ffaf815f8c2240d49c54aaddc70937a29ef0c40919d31acfed | J78: 通過 | O78: 否 | T78: =IF(J78="","未填",IF(J78="需複審",IF(OR(P78="",P78="仍需複審"),"待複審",P78),J78)) -> 通過 | U78: =IF(T78="通過",E78,IF(T78="需更正",IF(J78="需複審",IF(Q78="",E78,Q78),IF(L78="",E78,L78)),"")) -> 一張濕的， | V78: =IF(T78="通過",F78,IF(T78="需更正",IF(J78="需複審",R78,M78),"")) -> 水/一 | W78: =IF(AND(OR(T78="通過",AND(T78="需更正",V78<>"")),X78="通過"),"是","否") -> 是 | X78: =IF(J78="","未填",IF(AND(J78="需複審",OR(P78="",P78="仍需複審")),"待複審",IF(OR(AND(J78="需更正",K78=""),AND(J78="需更正",M78=""),AND(J78="需更正",N78=""),AND(J78="排除",OR(K78="",N78="")),AND(J78="需複審",P78="需更正",R78=""),AND(J78="需複審",P78="需更正",S78=""),AND(J78="需複審",P78="排除",S78="")),"錯誤：請補齊必填欄位","通過"))) -> 通過
A79: TC00078 | B79: TC00078 | C79: 文化部臺灣手語語料庫 | D79: 日常起居 | E79: 將濕抹布擰乾後擦窗戶再刮乾， | F79: 窗戶/抹布/水/擰乾/窗戶+抹布+擦/窗戶+刮刀+刮 | G79: G4D2P1/a151｜篇章1段落1｜臺灣手語語料庫（測試版），文化部，https://tslcorpus.moc.gov.tw/ | H79: https://tslcorpus.moc.gov.tw/upload/24/web/video/LJhgFLDWoNQPbQHZ.mp4 | I79: d0d8b2c9e72378eca65d99e7b580f7b99bf640c5c36659f45610af4860072f13 | J79: 通過 | O79: 否 | T79: =IF(J79="","未填",IF(J79="需複審",IF(OR(P79="",P79="仍需複審"),"待複審",P79),J79)) -> 通過 | U79: =IF(T79="通過",E79,IF(T79="需更正",IF(J79="需複審",IF(Q79="",E79,Q79),IF(L79="",E79,L79)),"")) -> 將濕抹布擰乾後擦窗戶再刮乾， | V79: =IF(T79="通過",F79,IF(T79="需更正",IF(J79="需複審",R79,M79),"")) -> 窗戶/抹布/水/擰乾/窗戶+抹布+擦/窗戶+刮刀+刮 | W79: =IF(AND(OR(T79="通過",AND(T79="需更正",V79<>"")),X79="通過"),"是","否") -> 是 | X79: =IF(J79="","未填",IF(AND(J79="需複審",OR(P79="",P79="仍需複審")),"待複審",IF(OR(AND(J79="需更正",K79=""),AND(J79="需更正",M79=""),AND(J79="需更正",N79=""),AND(J79="排除",OR(K79="",N79="")),AND(J79="需複審",P79="需更正",R79=""),AND(J79="需複審",P79="需更正",S79=""),AND(J79="需複審",P79="排除",S79="")),"錯誤：請補齊必填欄位","通過"))) -> 通過
A80: TC00079 | B80: TC00079 | C80: 文化部臺灣手語語料庫 | D80: 日常起居 | E80: 接著用乾抹布將四周擦乾淨。 | F80: 接下來/抹布/乾/窗戶+抹布+擦四周/乾淨/亮晶晶 | G80: G4D2P1/a152｜篇章1段落1｜臺灣手語語料庫（測試版），文化部，https://tslcorpus.moc.gov.tw/ | H80: https://tslcorpus.moc.gov.tw/upload/24/web/video/LJhgFLDWoNQPbQHZ.mp4 | I80: 1ca6064b5302d6b232343ec0986705aec0b09c746f3cd45b077a9f0ded9048a2 | J80: 通過 | O80: 否 | T80: =IF(J80="","未填",IF(J80="需複審",IF(OR(P80="",P80="仍需複審"),"待複審",P80),J80)) -> 通過 | U80: =IF(T80="通過",E80,IF(T80="需更正",IF(J80="需複審",IF(Q80="",E80,Q80),IF(L80="",E80,L80)),"")) -> 接著用乾抹布將四周擦乾淨。 | V80: =IF(T80="通過",F80,IF(T80="需更正",IF(J80="需複審",R80,M80),"")) -> 接下來/抹布/乾/窗戶+抹布+擦四周/乾淨/亮晶晶 | W80: =IF(AND(OR(T80="通過",AND(T80="需更正",V80<>"")),X80="通過"),"是","否") -> 是 | X80: =IF(J80="","未填",IF(AND(J80="需複審",OR(P80="",P80="仍需複審")),"待複審",IF(OR(AND(J80="需更正",K80=""),AND(J80="需更正",M80=""),AND(J80="需更正",N80=""),AND(J80="排除",OR(K80="",N80="")),AND(J80="需複審",P80="需更正",R80=""),AND(J80="需複審",P80="需更正",S80=""),AND(J80="需複審",P80="排除",S80="")),"錯誤：請補齊必填欄位","通過"))) -> 通過
A81: TC00080 | B81: TC00080 | C81: 文化部臺灣手語語料庫 | D81: 日常起居 | E81: 再將窗溝的灰塵掃乾淨就好了。 | F81: 再/窗溝/灰塵+窗溝/髒污+窗溝/掃+窗溝/乾淨/完 | G81: G4D2P1/a153｜篇章1段落1｜臺灣手語語料庫（測試版），文化部，https://tslcorpus.moc.gov.tw/ | H81: https://tslcorpus.moc.gov.tw/upload/24/web/video/LJhgFLDWoNQPbQHZ.mp4 | I81: 39f1e3f35da87745a468bacb866d89c673520832931a7333038d63a6986fea8e | J81: 通過 | O81: 否 | T81: =IF(J81="","未填",IF(J81="需複審",IF(OR(P81="",P81="仍需複審"),"待複審",P81),J81)) -> 通過 | U81: =IF(T81="通過",E81,IF(T81="需更正",IF(J81="需複審",IF(Q81="",E81,Q81),IF(L81="",E81,L81)),"")) -> 再將窗溝的灰塵掃乾淨就好了。 | V81: =IF(T81="通過",F81,IF(T81="需更正",IF(J81="需複審",R81,M81),"")) -> 再/窗溝/灰塵+窗溝/髒污+窗溝/掃+窗溝/乾淨/完 | W81: =IF(AND(OR(T81="通過",AND(T81="需更正",V81<>"")),X81="通過"),"是","否") -> 是 | X81: =IF(J81="","未填",IF(AND(J81="需複審",OR(P81="",P81="仍需複審")),"待複審",IF(OR(AND(J81="需更正",K81=""),AND(J81="需更正",M81=""),AND(J81="需更正",N81=""),AND(J81="排除",OR(K81="",N81="")),AND(J81="需複審",P81="需更正",R81=""),AND(J81="需複審",P81="需更正",S81=""),AND(J81="需複審",P81="排除",S81="")),"錯誤：請補齊必填欄位","通過"))) -> 通過
A82: TC00081 | B82: TC00081 | C82: 文化部臺灣手語語料庫 | D82: 社交人際 | E82: 我以前在臺南啟聰學校讀國小、國中、高中， | F82: 我/以前/臺南/聾/學校/國小/國中/高中 | G82: G4D4P1/a49｜篇章1段落1｜臺灣手語語料庫（測試版），文化部，https://tslcorpus.moc.gov.tw/ | H82: https://tslcorpus.moc.gov.tw/upload/24/web/video/f0FYZ4v0Ea0TP7By.mp4 | I82: 35d04abd2a2d37cc2aa2feb23098f915837ff70034f3a111a09e23d8616486f6 | J82: 需更正 | K82: 漏詞 | M82: 我/以前/臺南/聾/學校/國小/國中/高中/念書 | N82: 漏詞 | O82: 否 | T82: =IF(J82="","未填",IF(J82="需複審",IF(OR(P82="",P82="仍需複審"),"待複審",P82),J82)) -> 需更正 | U82: =IF(T82="通過",E82,IF(T82="需更正",IF(J82="需複審",IF(Q82="",E82,Q82),IF(L82="",E82,L82)),"")) -> 我以前在臺南啟聰學校讀國小、國中、高中， | V82: =IF(T82="通過",F82,IF(T82="需更正",IF(J82="需複審",R82,M82),"")) -> 我/以前/臺南/聾/學校/國小/國中/高中/念書 | W82: =IF(AND(OR(T82="通過",AND(T82="需更正",V82<>"")),X82="通過"),"是","否") -> 是 | X82: =IF(J82="","未填",IF(AND(J82="需複審",OR(P82="",P82="仍需複審")),"待複審",IF(OR(AND(J82="需更正",K82=""),AND(J82="需更正",M82=""),AND(J82="需更正",N82=""),AND(J82="排除",OR(K82="",N82="")),AND(J82="需複審",P82="需更正",R82=""),AND(J82="需複審",P82="需更正",S82=""),AND(J82="需複審",P82="排除",S82="")),"錯誤：請補齊必填欄位","通過"))) -> 通過
A83: TC00082 | B83: TC00082 | C83: 文化部臺灣手語語料庫 | D83: 社交人際 | E83: 不管是學長姊或學弟妹， | F83: 念書/不管/學長姊/學弟妹 | G83: G4D4P1/a50｜篇章1段落1｜臺灣手語語料庫（測試版），文化部，https://tslcorpus.moc.gov.tw/ | H83: https://tslcorpus.moc.gov.tw/upload/24/web/video/f0FYZ4v0Ea0TP7By.mp4 | I83: 418aeef8c64aa707a050ca76a3f1cd82705e68a48c0f068b1facb2eedf12e7b9 | J83: 需更正 | K83: 多餘詞 | M83: 不管/學長姊/學弟妹 | N83: 多餘詞 | O83: 否 | T83: =IF(J83="","未填",IF(J83="需複審",IF(OR(P83="",P83="仍需複審"),"待複審",P83),J83)) -> 需更正 | U83: =IF(T83="通過",E83,IF(T83="需更正",IF(J83="需複審",IF(Q83="",E83,Q83),IF(L83="",E83,L83)),"")) -> 不管是學長姊或學弟妹， | V83: =IF(T83="通過",F83,IF(T83="需更正",IF(J83="需複審",R83,M83),"")) -> 不管/學長姊/學弟妹 | W83: =IF(AND(OR(T83="通過",AND(T83="需更正",V83<>"")),X83="通過"),"是","否") -> 是 | X83: =IF(J83="","未填",IF(AND(J83="需複審",OR(P83="",P83="仍需複審")),"待複審",IF(OR(AND(J83="需更正",K83=""),AND(J83="需更正",M83=""),AND(J83="需更正",N83=""),AND(J83="排除",OR(K83="",N83="")),AND(J83="需複審",P83="需更正",R83=""),AND(J83="需複審",P83="需更正",S83=""),AND(J83="需複審",P83="排除",S83="")),"錯誤：請補齊必填欄位","通過"))) -> 通過
A84: TC00083 | B84: TC00083 | C84: 文化部臺灣手語語料庫 | D84: 社交人際 | E84: 大家主要都是使用手語溝通， | F84: 溝通/聊天/手語/主要 | G84: G4D4P1/a314｜篇章1段落1｜臺灣手語語料庫（測試版），文化部，https://tslcorpus.moc.gov.tw/ | H84: https://tslcorpus.moc.gov.tw/upload/24/web/video/f0FYZ4v0Ea0TP7By.mp4 | I84: e93ee477d0f396c96931cf06d13ab52cec70d62fc8431ff9809b3d5c52150338 | J84: 需更正 | K84: 漏詞 | M84: 溝通/聊天/手語/主要/是 | N84: 漏詞 | O84: 否 | T84: =IF(J84="","未填",IF(J84="需複審",IF(OR(P84="",P84="仍需複審"),"待複審",P84),J84)) -> 需更正 | U84: =IF(T84="通過",E84,IF(T84="需更正",IF(J84="需複審",IF(Q84="",E84,Q84),IF(L84="",E84,L84)),"")) -> 大家主要都是使用手語溝通， | V84: =IF(T84="通過",F84,IF(T84="需更正",IF(J84="需複審",R84,M84),"")) -> 溝通/聊天/手語/主要/是 | W84: =IF(AND(OR(T84="通過",AND(T84="需更正",V84<>"")),X84="通過"),"是","否") -> 是 | X84: =IF(J84="","未填",IF(AND(J84="需複審",OR(P84="",P84="仍需複審")),"待複審",IF(OR(AND(J84="需更正",K84=""),AND(J84="需更正",M84=""),AND(J84="需更正",N84=""),AND(J84="排除",OR(K84="",N84="")),AND(J84="需複審",P84="需更正",R84=""),AND(J84="需複審",P84="需更正",S84=""),AND(J84="需複審",P84="排除",S84="")),"錯誤：請補齊必填欄位","通過"))) -> 通過
A85: TC00084 | B85: TC00084 | C85: 文化部臺灣手語語料庫 | D85: 社交人際 | E85: 每天到學校跟大家見面， | F85: 是/每天/學校/見面 | G85: G4D4P1/a51｜篇章1段落1｜臺灣手語語料庫（測試版），文化部，https://tslcorpus.moc.gov.tw/ | H85: https://tslcorpus.moc.gov.tw/upload/24/web/video/f0FYZ4v0Ea0TP7By.mp4 | I85: 889e0244970b93635abd2a4b24fe0762de35d3212188c5d6f8732a107d03d52d | J85: 需更正 | K85: 多餘詞 | M85: 每天/學校/見面 | N85: 多餘詞 | O85: 否 | T85: =IF(J85="","未填",IF(J85="需複審",IF(OR(P85="",P85="仍需複審"),"待複審",P85),J85)) -> 需更正 | U85: =IF(T85="通過",E85,IF(T85="需更正",IF(J85="需複審",IF(Q85="",E85,Q85),IF(L85="",E85,L85)),"")) -> 每天到學校跟大家見面， | V85: =IF(T85="通過",F85,IF(T85="需更正",IF(J85="需複審",R85,M85),"")) -> 每天/學校/見面 | W85: =IF(AND(OR(T85="通過",AND(T85="需更正",V85<>"")),X85="通過"),"是","否") -> 是 | X85: =IF(J85="","未填",IF(AND(J85="需複審",OR(P85="",P85="仍需複審")),"待複審",IF(OR(AND(J85="需更正",K85=""),AND(J85="需更正",M85=""),AND(J85="需更正",N85=""),AND(J85="排除",OR(K85="",N85="")),AND(J85="需複審",P85="需更正",R85=""),AND(J85="需複審",P85="需更正",S85=""),AND(J85="需複審",P85="排除",S85="")),"錯誤：請補齊必填欄位","通過"))) -> 通過
A86: TC00085 | B86: TC00085 | C86: 文化部臺灣手語語料庫 | D86: 社交人際 | E86: 用手語聊天真的很開心。 | F86: 手語/聊天/快樂/棒 | G86: G4D4P1/a315｜篇章1段落1｜臺灣手語語料庫（測試版），文化部，https://tslcorpus.moc.gov.tw/ | H86: https://tslcorpus.moc.gov.tw/upload/24/web/video/f0FYZ4v0Ea0TP7By.mp4 | I86: 33ea9db594d4b927cac1eeaac34eca37b1fba4995a66cb39861da5f02bc5aa44 | J86: 通過 | O86: 否 | T86: =IF(J86="","未填",IF(J86="需複審",IF(OR(P86="",P86="仍需複審"),"待複審",P86),J86)) -> 通過 | U86: =IF(T86="通過",E86,IF(T86="需更正",IF(J86="需複審",IF(Q86="",E86,Q86),IF(L86="",E86,L86)),"")) -> 用手語聊天真的很開心。 | V86: =IF(T86="通過",F86,IF(T86="需更正",IF(J86="需複審",R86,M86),"")) -> 手語/聊天/快樂/棒 | W86: =IF(AND(OR(T86="通過",AND(T86="需更正",V86<>"")),X86="通過"),"是","否") -> 是 | X86: =IF(J86="","未填",IF(AND(J86="需複審",OR(P86="",P86="仍需複審")),"待複審",IF(OR(AND(J86="需更正",K86=""),AND(J86="需更正",M86=""),AND(J86="需更正",N86=""),AND(J86="排除",OR(K86="",N86="")),AND(J86="需複審",P86="需更正",R86=""),AND(J86="需複審",P86="需更正",S86=""),AND(J86="需複審",P86="排除",S86="")),"錯誤：請補齊必填欄位","通過"))) -> 通過
A87: TC00086 | B87: TC00086 | C87: 文化部臺灣手語語料庫 | D87: 文化 | E87: 回想我小時候， | F87: 想到/我/小時候 | G87: G4D3P1/a89｜篇章1段落1｜臺灣手語語料庫（測試版），文化部，https://tslcorpus.moc.gov.tw/ | H87: https://tslcorpus.moc.gov.tw/upload/24/web/video/We6VAmr96PLbcgGM.mp4 | I87: 67a168848a56f815cb198c4c9ac2b0bbc3c75de4f98c1cb92d2df392871da724 | J87: 通過 | O87: 否 | T87: =IF(J87="","未填",IF(J87="需複審",IF(OR(P87="",P87="仍需複審"),"待複審",P87),J87)) -> 通過 | U87: =IF(T87="通過",E87,IF(T87="需更正",IF(J87="需複審",IF(Q87="",E87,Q87),IF(L87="",E87,L87)),"")) -> 回想我小時候， | V87: =IF(T87="通過",F87,IF(T87="需更正",IF(J87="需複審",R87,M87),"")) -> 想到/我/小時候 | W87: =IF(AND(OR(T87="通過",AND(T87="需更正",V87<>"")),X87="通過"),"是","否") -> 是 | X87: =IF(J87="","未填",IF(AND(J87="需複審",OR(P87="",P87="仍需複審")),"待複審",IF(OR(AND(J87="需更正",K87=""),AND(J87="需更正",M87=""),AND(J87="需更正",N87=""),AND(J87="排除",OR(K87="",N87="")),AND(J87="需複審",P87="需更正",R87=""),AND(J87="需複審",P87="需更正",S87=""),AND(J87="需複審",P87="排除",S87="")),"錯誤：請補齊必填欄位","通過"))) -> 通過
A88: TC00087 | B88: TC00087 | C88: 文化部臺灣手語語料庫 | D88: 文化 | E88: 剛開始去啟聰學校念小一的時候。 | F88: 起初/去/聾/學校/念書/從國小一年級開始 | G88: G4D3P1/a90｜篇章1段落1｜臺灣手語語料庫（測試版），文化部，https://tslcorpus.moc.gov.tw/ | H88: https://tslcorpus.moc.gov.tw/upload/24/web/video/We6VAmr96PLbcgGM.mp4 | I88: b2d047ee1262f3138b837eb07b9eba4a3e990598bea0208b623f3f8f78e1afb0 | J88: 通過 | O88: 否 | T88: =IF(J88="","未填",IF(J88="需複審",IF(OR(P88="",P88="仍需複審"),"待複審",P88),J88)) -> 通過 | U88: =IF(T88="通過",E88,IF(T88="需更正",IF(J88="需複審",IF(Q88="",E88,Q88),IF(L88="",E88,L88)),"")) -> 剛開始去啟聰學校念小一的時候。 | V88: =IF(T88="通過",F88,IF(T88="需更正",IF(J88="需複審",R88,M88),"")) -> 起初/去/聾/學校/念書/從國小一年級開始 | W88: =IF(AND(OR(T88="通過",AND(T88="需更正",V88<>"")),X88="通過"),"是","否") -> 是 | X88: =IF(J88="","未填",IF(AND(J88="需複審",OR(P88="",P88="仍需複審")),"待複審",IF(OR(AND(J88="需更正",K88=""),AND(J88="需更正",M88=""),AND(J88="需更正",N88=""),AND(J88="排除",OR(K88="",N88="")),AND(J88="需複審",P88="需更正",R88=""),AND(J88="需複審",P88="需更正",S88=""),AND(J88="需複審",P88="排除",S88="")),"錯誤：請補齊必填欄位","通過"))) -> 通過
A89: TC00088 | B89: TC00088 | C89: 文化部臺灣手語語料庫 | D89: 文化 | E89: 當時我年幼無知， | F89: 那時/我/年幼/事情/什麼/不知道 | G89: G4D3P1/a91｜篇章1段落1｜臺灣手語語料庫（測試版），文化部，https://tslcorpus.moc.gov.tw/ | H89: https://tslcorpus.moc.gov.tw/upload/24/web/video/We6VAmr96PLbcgGM.mp4 | I89: 644a9a6825c87d45f012af511a5ba0e8b1af898b6682bad99d45308abde2ed7d | J89: 通過 | O89: 否 | T89: =IF(J89="","未填",IF(J89="需複審",IF(OR(P89="",P89="仍需複審"),"待複審",P89),J89)) -> 通過 | U89: =IF(T89="通過",E89,IF(T89="需更正",IF(J89="需複審",IF(Q89="",E89,Q89),IF(L89="",E89,L89)),"")) -> 當時我年幼無知， | V89: =IF(T89="通過",F89,IF(T89="需更正",IF(J89="需複審",R89,M89),"")) -> 那時/我/年幼/事情/什麼/不知道 | W89: =IF(AND(OR(T89="通過",AND(T89="需更正",V89<>"")),X89="通過"),"是","否") -> 是 | X89: =IF(J89="","未填",IF(AND(J89="需複審",OR(P89="",P89="仍需複審")),"待複審",IF(OR(AND(J89="需更正",K89=""),AND(J89="需更正",M89=""),AND(J89="需更正",N89=""),AND(J89="排除",OR(K89="",N89="")),AND(J89="需複審",P89="需更正",R89=""),AND(J89="需複審",P89="需更正",S89=""),AND(J89="需複審",P89="排除",S89="")),"錯誤：請補齊必填欄位","通過"))) -> 通過
A90: TC00089 | B90: TC00089 | C90: 文化部臺灣手語語料庫 | D90: 文化 | E90: 老師帶我進入教室， | F90: 老師/帶/教室 | G90: G4D3P1/a92｜篇章1段落1｜臺灣手語語料庫（測試版），文化部，https://tslcorpus.moc.gov.tw/ | H90: https://tslcorpus.moc.gov.tw/upload/24/web/video/We6VAmr96PLbcgGM.mp4 | I90: 1c5e14f69b00088ded614b297661c163c2fd5cc5ed3051185afa8011b7354abb | J90: 通過 | O90: 否 | T90: =IF(J90="","未填",IF(J90="需複審",IF(OR(P90="",P90="仍需複審"),"待複審",P90),J90)) -> 通過 | U90: =IF(T90="通過",E90,IF(T90="需更正",IF(J90="需複審",IF(Q90="",E90,Q90),IF(L90="",E90,L90)),"")) -> 老師帶我進入教室， | V90: =IF(T90="通過",F90,IF(T90="需更正",IF(J90="需複審",R90,M90),"")) -> 老師/帶/教室 | W90: =IF(AND(OR(T90="通過",AND(T90="需更正",V90<>"")),X90="通過"),"是","否") -> 是 | X90: =IF(J90="","未填",IF(AND(J90="需複審",OR(P90="",P90="仍需複審")),"待複審",IF(OR(AND(J90="需更正",K90=""),AND(J90="需更正",M90=""),AND(J90="需更正",N90=""),AND(J90="排除",OR(K90="",N90="")),AND(J90="需複審",P90="需更正",R90=""),AND(J90="需複審",P90="需更正",S90=""),AND(J90="需複審",P90="排除",S90="")),"錯誤：請補齊必填欄位","通過"))) -> 通過
A91: TC00090 | B91: TC00090 | C91: 文化部臺灣手語語料庫 | D91: 文化 | E91: 我看見黑板上有紅燈和綠燈， | F91: 黑板/看見/紅燈 | G91: G4D3P1/a93｜篇章1段落1｜臺灣手語語料庫（測試版），文化部，https://tslcorpus.moc.gov.tw/ | H91: https://tslcorpus.moc.gov.tw/upload/24/web/video/We6VAmr96PLbcgGM.mp4 | I91: e1fff99eb2a6a8619959cd6a71c6f6b0178c3228270a652642543086f8a71c48 | J91: 需更正 | K91: 漏詞 | M91: 黑板/看見/紅燈/綠燈 | N91: 漏詞 | O91: 否 | T91: =IF(J91="","未填",IF(J91="需複審",IF(OR(P91="",P91="仍需複審"),"待複審",P91),J91)) -> 需更正 | U91: =IF(T91="通過",E91,IF(T91="需更正",IF(J91="需複審",IF(Q91="",E91,Q91),IF(L91="",E91,L91)),"")) -> 我看見黑板上有紅燈和綠燈， | V91: =IF(T91="通過",F91,IF(T91="需更正",IF(J91="需複審",R91,M91),"")) -> 黑板/看見/紅燈/綠燈 | W91: =IF(AND(OR(T91="通過",AND(T91="需更正",V91<>"")),X91="通過"),"是","否") -> 是 | X91: =IF(J91="","未填",IF(AND(J91="需複審",OR(P91="",P91="仍需複審")),"待複審",IF(OR(AND(J91="需更正",K91=""),AND(J91="需更正",M91=""),AND(J91="需更正",N91=""),AND(J91="排除",OR(K91="",N91="")),AND(J91="需複審",P91="需更正",R91=""),AND(J91="需複審",P91="需更正",S91=""),AND(J91="需複審",P91="排除",S91="")),"錯誤：請補齊必填欄位","通過"))) -> 通過
A92: TC00091 | B92: TC00091 | C92: 文化部臺灣手語語料庫 | D92: 文化 | E92: 我當時還小看不懂， | F92: 綠燈/我/小孩/看/不知道 | G92: G4D3P1/a94｜篇章1段落1｜臺灣手語語料庫（測試版），文化部，https://tslcorpus.moc.gov.tw/ | H92: https://tslcorpus.moc.gov.tw/upload/24/web/video/We6VAmr96PLbcgGM.mp4 | I92: bdd2d4d592daeb65fab4b369caa8467d2f5192607d4c8255c34f461324a443de | J92: 需更正 | K92: 多餘詞 | M92: 我/小孩/看/不知道 | N92: 多餘詞 | O92: 否 | T92: =IF(J92="","未填",IF(J92="需複審",IF(OR(P92="",P92="仍需複審"),"待複審",P92),J92)) -> 需更正 | U92: =IF(T92="通過",E92,IF(T92="需更正",IF(J92="需複審",IF(Q92="",E92,Q92),IF(L92="",E92,L92)),"")) -> 我當時還小看不懂， | V92: =IF(T92="通過",F92,IF(T92="需更正",IF(J92="需複審",R92,M92),"")) -> 我/小孩/看/不知道 | W92: =IF(AND(OR(T92="通過",AND(T92="需更正",V92<>"")),X92="通過"),"是","否") -> 是 | X92: =IF(J92="","未填",IF(AND(J92="需複審",OR(P92="",P92="仍需複審")),"待複審",IF(OR(AND(J92="需更正",K92=""),AND(J92="需更正",M92=""),AND(J92="需更正",N92=""),AND(J92="排除",OR(K92="",N92="")),AND(J92="需複審",P92="需更正",R92=""),AND(J92="需複審",P92="需更正",S92=""),AND(J92="需複審",P92="排除",S92="")),"錯誤：請補齊必填欄位","通過"))) -> 通過
A93: TC00092 | B93: TC00092 | C93: 文化部臺灣手語語料庫 | D93: 文化 | E93: 也沒有專心， | F93: 專心/沒有 | G93: G4D3P1/a95｜篇章1段落1｜臺灣手語語料庫（測試版），文化部，https://tslcorpus.moc.gov.tw/ | H93: https://tslcorpus.moc.gov.tw/upload/24/web/video/We6VAmr96PLbcgGM.mp4 | I93: d08dbc869411abe565f5e34404c3ac70509fa4111a0104d8257fe59b6a832a95 | J93: 通過 | O93: 否 | T93: =IF(J93="","未填",IF(J93="需複審",IF(OR(P93="",P93="仍需複審"),"待複審",P93),J93)) -> 通過 | U93: =IF(T93="通過",E93,IF(T93="需更正",IF(J93="需複審",IF(Q93="",E93,Q93),IF(L93="",E93,L93)),"")) -> 也沒有專心， | V93: =IF(T93="通過",F93,IF(T93="需更正",IF(J93="需複審",R93,M93),"")) -> 專心/沒有 | W93: =IF(AND(OR(T93="通過",AND(T93="需更正",V93<>"")),X93="通過"),"是","否") -> 是 | X93: =IF(J93="","未填",IF(AND(J93="需複審",OR(P93="",P93="仍需複審")),"待複審",IF(OR(AND(J93="需更正",K93=""),AND(J93="需更正",M93=""),AND(J93="需更正",N93=""),AND(J93="排除",OR(K93="",N93="")),AND(J93="需複審",P93="需更正",R93=""),AND(J93="需複審",P93="需更正",S93=""),AND(J93="需複審",P93="排除",S93="")),"錯誤：請補齊必填欄位","通過"))) -> 通過
A94: TC00093 | B94: TC00093 | C94: 文化部臺灣手語語料庫 | D94: 文化 | E94: 就看著那亮著的紅燈。 | F94: 我/看到/紅燈亮/仍然 | G94: G4D3P1/a96｜篇章1段落1｜臺灣手語語料庫（測試版），文化部，https://tslcorpus.moc.gov.tw/ | H94: https://tslcorpus.moc.gov.tw/upload/24/web/video/We6VAmr96PLbcgGM.mp4 | I94: 3f2a8f6ab5979b9df7ec82035f23ef95a32ebd2faed6d34704aa10ef13ee2c71 | J94: 通過 | O94: 否 | T94: =IF(J94="","未填",IF(J94="需複審",IF(OR(P94="",P94="仍需複審"),"待複審",P94),J94)) -> 通過 | U94: =IF(T94="通過",E94,IF(T94="需更正",IF(J94="需複審",IF(Q94="",E94,Q94),IF(L94="",E94,L94)),"")) -> 就看著那亮著的紅燈。 | V94: =IF(T94="通過",F94,IF(T94="需更正",IF(J94="需複審",R94,M94),"")) -> 我/看到/紅燈亮/仍然 | W94: =IF(AND(OR(T94="通過",AND(T94="需更正",V94<>"")),X94="通過"),"是","否") -> 是 | X94: =IF(J94="","未填",IF(AND(J94="需複審",OR(P94="",P94="仍需複審")),"待複審",IF(OR(AND(J94="需更正",K94=""),AND(J94="需更正",M94=""),AND(J94="需更正",N94=""),AND(J94="排除",OR(K94="",N94="")),AND(J94="需複審",P94="需更正",R94=""),AND(J94="需複審",P94="需更正",S94=""),AND(J94="需複審",P94="排除",S94="")),"錯誤：請補齊必填欄位","通過"))) -> 通過
A95: TC00094 | B95: TC00094 | C95: 文化部臺灣手語語料庫 | D95: 文化 | E95: 老師告訴我們小朋友們要認真坐好， | F95: 老師/告訴/孩子/招/坐/認真 | G95: G4D3P1/a97｜篇章1段落1｜臺灣手語語料庫（測試版），文化部，https://tslcorpus.moc.gov.tw/ | H95: https://tslcorpus.moc.gov.tw/upload/24/web/video/We6VAmr96PLbcgGM.mp4 | I95: 1a000f8b91f1caf3d7fdd541977a8ae17bd7a837e13a51bae21704eb80065fa0 | J95: 通過 | O95: 否 | T95: =IF(J95="","未填",IF(J95="需複審",IF(OR(P95="",P95="仍需複審"),"待複審",P95),J95)) -> 通過 | U95: =IF(T95="通過",E95,IF(T95="需更正",IF(J95="需複審",IF(Q95="",E95,Q95),IF(L95="",E95,L95)),"")) -> 老師告訴我們小朋友們要認真坐好， | V95: =IF(T95="通過",F95,IF(T95="需更正",IF(J95="需複審",R95,M95),"")) -> 老師/告訴/孩子/招/坐/認真 | W95: =IF(AND(OR(T95="通過",AND(T95="需更正",V95<>"")),X95="通過"),"是","否") -> 是 | X95: =IF(J95="","未填",IF(AND(J95="需複審",OR(P95="",P95="仍需複審")),"待複審",IF(OR(AND(J95="需更正",K95=""),AND(J95="需更正",M95=""),AND(J95="需更正",N95=""),AND(J95="排除",OR(K95="",N95="")),AND(J95="需複審",P95="需更正",R95=""),AND(J95="需複審",P95="需更正",S95=""),AND(J95="需複審",P95="排除",S95="")),"錯誤：請補齊必填欄位","通過"))) -> 通過
A96: TC00095 | B96: TC00095 | C96: 文化部臺灣手語語料庫 | D96: 文化 | E96: 然後在黑板上寫字， | F96: 黑板/老師/寫 | G96: G4D3P1/a98｜篇章1段落1｜臺灣手語語料庫（測試版），文化部，https://tslcorpus.moc.gov.tw/ | H96: https://tslcorpus.moc.gov.tw/upload/24/web/video/We6VAmr96PLbcgGM.mp4 | I96: 9f9938f765e9997c34d3ecd51f87ff771d5eb7b5bc119858129ae12a85c3c3e4 | J96: 通過 | O96: 否 | T96: =IF(J96="","未填",IF(J96="需複審",IF(OR(P96="",P96="仍需複審"),"待複審",P96),J96)) -> 通過 | U96: =IF(T96="通過",E96,IF(T96="需更正",IF(J96="需複審",IF(Q96="",E96,Q96),IF(L96="",E96,L96)),"")) -> 然後在黑板上寫字， | V96: =IF(T96="通過",F96,IF(T96="需更正",IF(J96="需複審",R96,M96),"")) -> 黑板/老師/寫 | W96: =IF(AND(OR(T96="通過",AND(T96="需更正",V96<>"")),X96="通過"),"是","否") -> 是 | X96: =IF(J96="","未填",IF(AND(J96="需複審",OR(P96="",P96="仍需複審")),"待複審",IF(OR(AND(J96="需更正",K96=""),AND(J96="需更正",M96=""),AND(J96="需更正",N96=""),AND(J96="排除",OR(K96="",N96="")),AND(J96="需複審",P96="需更正",R96=""),AND(J96="需複審",P96="需更正",S96=""),AND(J96="需複審",P96="排除",S96="")),"錯誤：請補齊必填欄位","通過"))) -> 通過
A97: TC00096 | B97: TC00096 | C97: 文化部臺灣手語語料庫 | D97: 文化 | E97: 讓我們在底下抄寫。 | F97: 我們/寫/學 | G97: G4D3P1/a99｜篇章1段落1｜臺灣手語語料庫（測試版），文化部，https://tslcorpus.moc.gov.tw/ | H97: https://tslcorpus.moc.gov.tw/upload/24/web/video/We6VAmr96PLbcgGM.mp4 | I97: 5af0311ceedeb89e8e57fe87458d79d289ab184adb3d7f5761e8488a67b7a682 | J97: 通過 | O97: 否 | T97: =IF(J97="","未填",IF(J97="需複審",IF(OR(P97="",P97="仍需複審"),"待複審",P97),J97)) -> 通過 | U97: =IF(T97="通過",E97,IF(T97="需更正",IF(J97="需複審",IF(Q97="",E97,Q97),IF(L97="",E97,L97)),"")) -> 讓我們在底下抄寫。 | V97: =IF(T97="通過",F97,IF(T97="需更正",IF(J97="需複審",R97,M97),"")) -> 我們/寫/學 | W97: =IF(AND(OR(T97="通過",AND(T97="需更正",V97<>"")),X97="通過"),"是","否") -> 是 | X97: =IF(J97="","未填",IF(AND(J97="需複審",OR(P97="",P97="仍需複審")),"待複審",IF(OR(AND(J97="需更正",K97=""),AND(J97="需更正",M97=""),AND(J97="需更正",N97=""),AND(J97="排除",OR(K97="",N97="")),AND(J97="需複審",P97="需更正",R97=""),AND(J97="需複審",P97="需更正",S97=""),AND(J97="需複審",P97="排除",S97="")),"錯誤：請補齊必填欄位","通過"))) -> 通過
A98: TC00097 | B98: TC00097 | C98: 文化部臺灣手語語料庫 | D98: 安全 | E98: 大家都知道交通安全很重要， | F98: 交通/安全/重要/大家/知道 | G98: G3D3P1/a75｜篇章1段落1｜臺灣手語語料庫（測試版），文化部，https://tslcorpus.moc.gov.tw/ | H98: https://tslcorpus.moc.gov.tw/upload/24/web/video/phVZR3AGC8KFos1n.mp4 | I98: 043d268d80f7badcae7c8118c46206cc3bdf92fc3d9de7f8dc531ee2d75afc78 | J98: 通過 | O98: 否 | T98: =IF(J98="","未填",IF(J98="需複審",IF(OR(P98="",P98="仍需複審"),"待複審",P98),J98)) -> 通過 | U98: =IF(T98="通過",E98,IF(T98="需更正",IF(J98="需複審",IF(Q98="",E98,Q98),IF(L98="",E98,L98)),"")) -> 大家都知道交通安全很重要， | V98: =IF(T98="通過",F98,IF(T98="需更正",IF(J98="需複審",R98,M98),"")) -> 交通/安全/重要/大家/知道 | W98: =IF(AND(OR(T98="通過",AND(T98="需更正",V98<>"")),X98="通過"),"是","否") -> 是 | X98: =IF(J98="","未填",IF(AND(J98="需複審",OR(P98="",P98="仍需複審")),"待複審",IF(OR(AND(J98="需更正",K98=""),AND(J98="需更正",M98=""),AND(J98="需更正",N98=""),AND(J98="排除",OR(K98="",N98="")),AND(J98="需複審",P98="需更正",R98=""),AND(J98="需複審",P98="需更正",S98=""),AND(J98="需複審",P98="排除",S98="")),"錯誤：請補齊必填欄位","通過"))) -> 通過
A99: TC00098 | B99: TC00098 | C99: 文化部臺灣手語語料庫 | D99: 安全 | E99: 對於聾人來說要注意什麼呢？ | F99: 聾人/他們/要/注意/什麼 | G99: G3D3P1/a76｜篇章1段落1｜臺灣手語語料庫（測試版），文化部，https://tslcorpus.moc.gov.tw/ | H99: https://tslcorpus.moc.gov.tw/upload/24/web/video/phVZR3AGC8KFos1n.mp4 | I99: 04907a022e37871e30aac4a4035fd3b3fe13b805bb0b8fcc6132c3a5fd2d3481 | J99: 通過 | O99: 否 | T99: =IF(J99="","未填",IF(J99="需複審",IF(OR(P99="",P99="仍需複審"),"待複審",P99),J99)) -> 通過 | U99: =IF(T99="通過",E99,IF(T99="需更正",IF(J99="需複審",IF(Q99="",E99,Q99),IF(L99="",E99,L99)),"")) -> 對於聾人來說要注意什麼呢？ | V99: =IF(T99="通過",F99,IF(T99="需更正",IF(J99="需複審",R99,M99),"")) -> 聾人/他們/要/注意/什麼 | W99: =IF(AND(OR(T99="通過",AND(T99="需更正",V99<>"")),X99="通過"),"是","否") -> 是 | X99: =IF(J99="","未填",IF(AND(J99="需複審",OR(P99="",P99="仍需複審")),"待複審",IF(OR(AND(J99="需更正",K99=""),AND(J99="需更正",M99=""),AND(J99="需更正",N99=""),AND(J99="排除",OR(K99="",N99="")),AND(J99="需複審",P99="需更正",R99=""),AND(J99="需複審",P99="需更正",S99=""),AND(J99="需複審",P99="排除",S99="")),"錯誤：請補齊必填欄位","通過"))) -> 通過
A100: TC00099 | B100: TC00099 | C100: 文化部臺灣手語語料庫 | D100: 安全 | E100: 我們從在路上行走和搭車兩個方面來探討： | F100: 路/走/上車/這兩個/事情/我們/一起/討論 | G100: G3D3P1/a77｜篇章1段落1｜臺灣手語語料庫（測試版），文化部，https://tslcorpus.moc.gov.tw/ | H100: https://tslcorpus.moc.gov.tw/upload/24/web/video/phVZR3AGC8KFos1n.mp4 | I100: 7b6bd9f0fcf3a5303fc6e1bb8e682c62bff500abcb01416ed97123fdb0945039 | J100: 通過 | O100: 否 | T100: =IF(J100="","未填",IF(J100="需複審",IF(OR(P100="",P100="仍需複審"),"待複審",P100),J100)) -> 通過 | U100: =IF(T100="通過",E100,IF(T100="需更正",IF(J100="需複審",IF(Q100="",E100,Q100),IF(L100="",E100,L100)),"")) -> 我們從在路上行走和搭車兩個方面來探討： | V100: =IF(T100="通過",F100,IF(T100="需更正",IF(J100="需複審",R100,M100),"")) -> 路/走/上車/這兩個/事情/我們/一起/討論 | W100: =IF(AND(OR(T100="通過",AND(T100="需更正",V100<>"")),X100="通過"),"是","否") -> 是 | X100: =IF(J100="","未填",IF(AND(J100="需複審",OR(P100="",P100="仍需複審")),"待複審",IF(OR(AND(J100="需更正",K100=""),AND(J100="需更正",M100=""),AND(J100="需更正",N100=""),AND(J100="排除",OR(K100="",N100="")),AND(J100="需複審",P100="需更正",R100=""),AND(J100="需複審",P100="需更正",S100=""),AND(J100="需複審",P100="排除",S100="")),"錯誤：請補齊必填欄位","通過"))) -> 通過
A101: TC00100 | B101: TC00100 | C101: 文化部臺灣手語語料庫 | D101: 安全 | E101: 行走時，如果有人騎腳踏車按鈴要借過， | F101: 走/時候/如果/有人/騎腳踏車/見到/按車鈴++ | G101: G3D3P1/a78｜篇章1段落1｜臺灣手語語料庫（測試版），文化部，https://tslcorpus.moc.gov.tw/ | H101: https://tslcorpus.moc.gov.tw/upload/24/web/video/phVZR3AGC8KFos1n.mp4 | I101: 4a0fa547564ea9889fc96b3dbe85ea737aee684fc5dcb9a991de167230a9636a | J101: 通過 | O101: 否 | T101: =IF(J101="","未填",IF(J101="需複審",IF(OR(P101="",P101="仍需複審"),"待複審",P101),J101)) -> 通過 | U101: =IF(T101="通過",E101,IF(T101="需更正",IF(J101="需複審",IF(Q101="",E101,Q101),IF(L101="",E101,L101)),"")) -> 行走時，如果有人騎腳踏車按鈴要借過， | V101: =IF(T101="通過",F101,IF(T101="需更正",IF(J101="需複審",R101,M101),"")) -> 走/時候/如果/有人/騎腳踏車/見到/按車鈴++ | W101: =IF(AND(OR(T101="通過",AND(T101="需更正",V101<>"")),X101="通過"),"是","否") -> 是 | X101: =IF(J101="","未填",IF(AND(J101="需複審",OR(P101="",P101="仍需複審")),"待複審",IF(OR(AND(J101="需更正",K101=""),AND(J101="需更正",M101=""),AND(J101="需更正",N101=""),AND(J101="排除",OR(K101="",N101="")),AND(J101="需複審",P101="需更正",R101=""),AND(J101="需複審",P101="需更正",S101=""),AND(J101="需複審",P101="排除",S101="")),"錯誤：請補齊必填欄位","通過"))) -> 通過
A102: TC00101 | B102: TC00101 | C102: 文化部臺灣手語語料庫 | D102: 安全 | E102: 聾人聽不到可能會發生危險。 | F102: 聾人/聽不見/危險/可能 | G102: G3D3P1/a79｜篇章1段落1｜臺灣手語語料庫（測試版），文化部，https://tslcorpus.moc.gov.tw/ | H102: https://tslcorpus.moc.gov.tw/upload/24/web/video/phVZR3AGC8KFos1n.mp4 | I102: c1027ac3e0a76f0e6728ff6ba5679497c9a9318bbd8ba5ff9c9996d1a89cb55b | J102: 通過 | O102: 否 | T102: =IF(J102="","未填",IF(J102="需複審",IF(OR(P102="",P102="仍需複審"),"待複審",P102),J102)) -> 通過 | U102: =IF(T102="通過",E102,IF(T102="需更正",IF(J102="需複審",IF(Q102="",E102,Q102),IF(L102="",E102,L102)),"")) -> 聾人聽不到可能會發生危險。 | V102: =IF(T102="通過",F102,IF(T102="需更正",IF(J102="需複審",R102,M102),"")) -> 聾人/聽不見/危險/可能 | W102: =IF(AND(OR(T102="通過",AND(T102="需更正",V102<>"")),X102="通過"),"是","否") -> 是 | X102: =IF(J102="","未填",IF(AND(J102="需複審",OR(P102="",P102="仍需複審")),"待複審",IF(OR(AND(J102="需更正",K102=""),AND(J102="需更正",M102=""),AND(J102="需更正",N102=""),AND(J102="排除",OR(K102="",N102="")),AND(J102="需複審",P102="需更正",R102=""),AND(J102="需複審",P102="需更正",S102=""),AND(J102="需複審",P102="排除",S102="")),"錯誤：請補齊必填欄位","通過"))) -> 通過
A103: TC00102 | B103: TC00102 | C103: 文化部臺灣手語語料庫 | D103: 安全 | E103: 如果身旁有聽人朋友，可以協助提醒聾人讓路。 | F103: 如果/旁邊/聽人/有/幫/告訴/讓路/可以 | G103: G3D3P1/a80｜篇章1段落1｜臺灣手語語料庫（測試版），文化部，https://tslcorpus.moc.gov.tw/ | H103: https://tslcorpus.moc.gov.tw/upload/24/web/video/phVZR3AGC8KFos1n.mp4 | I103: 81f74e7936419054738ab5a75ca506575093cd3aa13a205cf2994ff813364278 | J103: 通過 | O103: 否 | T103: =IF(J103="","未填",IF(J103="需複審",IF(OR(P103="",P103="仍需複審"),"待複審",P103),J103)) -> 通過 | U103: =IF(T103="通過",E103,IF(T103="需更正",IF(J103="需複審",IF(Q103="",E103,Q103),IF(L103="",E103,L103)),"")) -> 如果身旁有聽人朋友，可以協助提醒聾人讓路。 | V103: =IF(T103="通過",F103,IF(T103="需更正",IF(J103="需複審",R103,M103),"")) -> 如果/旁邊/聽人/有/幫/告訴/讓路/可以 | W103: =IF(AND(OR(T103="通過",AND(T103="需更正",V103<>"")),X103="通過"),"是","否") -> 是 | X103: =IF(J103="","未填",IF(AND(J103="需複審",OR(P103="",P103="仍需複審")),"待複審",IF(OR(AND(J103="需更正",K103=""),AND(J103="需更正",M103=""),AND(J103="需更正",N103=""),AND(J103="排除",OR(K103="",N103="")),AND(J103="需複審",P103="需更正",R103=""),AND(J103="需複審",P103="需更正",S103=""),AND(J103="需複審",P103="排除",S103="")),"錯誤：請補齊必填欄位","通過"))) -> 通過
A104: TC00103 | B104: TC00103 | C104: 文化部臺灣手語語料庫 | D104: 科技 | E104: 我們聾人以前用傳真機來聯繫。 | F104: 我們/聾人/以前/聯絡/這/什麼/傳真/這/是 | G104: G1D4P1/a87｜篇章1段落1｜臺灣手語語料庫（測試版），文化部，https://tslcorpus.moc.gov.tw/ | H104: https://tslcorpus.moc.gov.tw/upload/24/web/video/QfZZoRhC0gorifom.mp4 | I104: 7a3b1ebd906489f14309bc5781cf37c1cbe42ea0fdbaf0998ef157313e2163e9 | J104: 需更正 | K104: 多餘詞 | M104: 我們/聾人/以前/聯絡/傳真/這/是 | N104: 多餘詞 | O104: 否 | T104: =IF(J104="","未填",IF(J104="需複審",IF(OR(P104="",P104="仍需複審"),"待複審",P104),J104)) -> 需更正 | U104: =IF(T104="通過",E104,IF(T104="需更正",IF(J104="需複審",IF(Q104="",E104,Q104),IF(L104="",E104,L104)),"")) -> 我們聾人以前用傳真機來聯繫。 | V104: =IF(T104="通過",F104,IF(T104="需更正",IF(J104="需複審",R104,M104),"")) -> 我們/聾人/以前/聯絡/傳真/這/是 | W104: =IF(AND(OR(T104="通過",AND(T104="需更正",V104<>"")),X104="通過"),"是","否") -> 是 | X104: =IF(J104="","未填",IF(AND(J104="需複審",OR(P104="",P104="仍需複審")),"待複審",IF(OR(AND(J104="需更正",K104=""),AND(J104="需更正",M104=""),AND(J104="需更正",N104=""),AND(J104="排除",OR(K104="",N104="")),AND(J104="需複審",P104="需更正",R104=""),AND(J104="需複審",P104="需更正",S104=""),AND(J104="需複審",P104="排除",S104="")),"錯誤：請補齊必填欄位","通過"))) -> 通過
A105: TC00104 | B105: TC00104 | C105: 文化部臺灣手語語料庫 | D105: 科技 | E105: 不過在還沒有傳真機之前， | F105: 傳真機/還沒/之前 | G105: G1D4P1/a89｜篇章1段落1｜臺灣手語語料庫（測試版），文化部，https://tslcorpus.moc.gov.tw/ | H105: https://tslcorpus.moc.gov.tw/upload/24/web/video/QfZZoRhC0gorifom.mp4 | I105: c719c674d70af31e9b950447594338559e814e78785bfd7323812edb2ab729df | J105: 通過 | O105: 否 | T105: =IF(J105="","未填",IF(J105="需複審",IF(OR(P105="",P105="仍需複審"),"待複審",P105),J105)) -> 通過 | U105: =IF(T105="通過",E105,IF(T105="需更正",IF(J105="需複審",IF(Q105="",E105,Q105),IF(L105="",E105,L105)),"")) -> 不過在還沒有傳真機之前， | V105: =IF(T105="通過",F105,IF(T105="需更正",IF(J105="需複審",R105,M105),"")) -> 傳真機/還沒/之前 | W105: =IF(AND(OR(T105="通過",AND(T105="需更正",V105<>"")),X105="通過"),"是","否") -> 是 | X105: =IF(J105="","未填",IF(AND(J105="需複審",OR(P105="",P105="仍需複審")),"待複審",IF(OR(AND(J105="需更正",K105=""),AND(J105="需更正",M105=""),AND(J105="需更正",N105=""),AND(J105="排除",OR(K105="",N105="")),AND(J105="需複審",P105="需更正",R105=""),AND(J105="需複審",P105="需更正",S105=""),AND(J105="需複審",P105="排除",S105="")),"錯誤：請補齊必填欄位","通過"))) -> 通過
A106: TC00105 | B106: TC00105 | C106: 文化部臺灣手語語料庫 | D106: 科技 | E106: 只能用電話聯繫的時候， | F106: 電話/聯絡 | G106: G1D4P1/a90｜篇章1段落1｜臺灣手語語料庫（測試版），文化部，https://tslcorpus.moc.gov.tw/ | H106: https://tslcorpus.moc.gov.tw/upload/24/web/video/QfZZoRhC0gorifom.mp4 | I106: b89bc9dc1a1406100f218986714378f67d1ad21f18ee698e973e43b988c7a0ca | J106: 需更正 | K106: 漏詞 | M106: 電話/聯絡/這 | N106: 漏詞 | O106: 否 | T106: =IF(J106="","未填",IF(J106="需複審",IF(OR(P106="",P106="仍需複審"),"待複審",P106),J106)) -> 需更正 | U106: =IF(T106="通過",E106,IF(T106="需更正",IF(J106="需複審",IF(Q106="",E106,Q106),IF(L106="",E106,L106)),"")) -> 只能用電話聯繫的時候， | V106: =IF(T106="通過",F106,IF(T106="需更正",IF(J106="需複審",R106,M106),"")) -> 電話/聯絡/這 | W106: =IF(AND(OR(T106="通過",AND(T106="需更正",V106<>"")),X106="通過"),"是","否") -> 是 | X106: =IF(J106="","未填",IF(AND(J106="需複審",OR(P106="",P106="仍需複審")),"待複審",IF(OR(AND(J106="需更正",K106=""),AND(J106="需更正",M106=""),AND(J106="需更正",N106=""),AND(J106="排除",OR(K106="",N106="")),AND(J106="需複審",P106="需更正",R106=""),AND(J106="需複審",P106="需更正",S106=""),AND(J106="需複審",P106="排除",S106="")),"錯誤：請補齊必填欄位","通過"))) -> 通過
A107: TC00106 | B107: TC00106 | C107: 文化部臺灣手語語料庫 | D107: 科技 | E107: 我們只能麻煩認識的聽人幫忙。 | F107: 這/聽人/認識/派/幫 | G107: G1D4P1/a91｜篇章1段落1｜臺灣手語語料庫（測試版），文化部，https://tslcorpus.moc.gov.tw/ | H107: https://tslcorpus.moc.gov.tw/upload/24/web/video/QfZZoRhC0gorifom.mp4 | I107: fef480e07dfa59312c341dbf1ff4ddc5526096856ad71311ffabf4961d6807cf | J107: 需更正 | K107: 多餘詞 | M107: 聽人/認識/派/幫 | N107: 多餘詞 | O107: 否 | T107: =IF(J107="","未填",IF(J107="需複審",IF(OR(P107="",P107="仍需複審"),"待複審",P107),J107)) -> 需更正 | U107: =IF(T107="通過",E107,IF(T107="需更正",IF(J107="需複審",IF(Q107="",E107,Q107),IF(L107="",E107,L107)),"")) -> 我們只能麻煩認識的聽人幫忙。 | V107: =IF(T107="通過",F107,IF(T107="需更正",IF(J107="需複審",R107,M107),"")) -> 聽人/認識/派/幫 | W107: =IF(AND(OR(T107="通過",AND(T107="需更正",V107<>"")),X107="通過"),"是","否") -> 是 | X107: =IF(J107="","未填",IF(AND(J107="需複審",OR(P107="",P107="仍需複審")),"待複審",IF(OR(AND(J107="需更正",K107=""),AND(J107="需更正",M107=""),AND(J107="需更正",N107=""),AND(J107="排除",OR(K107="",N107="")),AND(J107="需複審",P107="需更正",R107=""),AND(J107="需複審",P107="需更正",S107=""),AND(J107="需複審",P107="排除",S107="")),"錯誤：請補齊必填欄位","通過"))) -> 通過
A108: TC00107 | B108: TC00107 | C108: 文化部臺灣手語語料庫 | D108: 科技 | E108: 但是如果人在外面， | F108: 如果/外面/路/走 | G108: G1D4P1/a92｜篇章1段落1｜臺灣手語語料庫（測試版），文化部，https://tslcorpus.moc.gov.tw/ | H108: https://tslcorpus.moc.gov.tw/upload/24/web/video/QfZZoRhC0gorifom.mp4 | I108: 455ba9072d80f027c364dd34a6dde79f7a63a7426875fb404599e061b9284789 | J108: 通過 | O108: 否 | T108: =IF(J108="","未填",IF(J108="需複審",IF(OR(P108="",P108="仍需複審"),"待複審",P108),J108)) -> 通過 | U108: =IF(T108="通過",E108,IF(T108="需更正",IF(J108="需複審",IF(Q108="",E108,Q108),IF(L108="",E108,L108)),"")) -> 但是如果人在外面， | V108: =IF(T108="通過",F108,IF(T108="需更正",IF(J108="需複審",R108,M108),"")) -> 如果/外面/路/走 | W108: =IF(AND(OR(T108="通過",AND(T108="需更正",V108<>"")),X108="通過"),"是","否") -> 是 | X108: =IF(J108="","未填",IF(AND(J108="需複審",OR(P108="",P108="仍需複審")),"待複審",IF(OR(AND(J108="需更正",K108=""),AND(J108="需更正",M108=""),AND(J108="需更正",N108=""),AND(J108="排除",OR(K108="",N108="")),AND(J108="需複審",P108="需更正",R108=""),AND(J108="需複審",P108="需更正",S108=""),AND(J108="需複審",P108="排除",S108="")),"錯誤：請補齊必填欄位","通過"))) -> 通過
A109: TC00108 | B109: TC00108 | C109: 文化部臺灣手語語料庫 | D109: 科技 | E109: 臨時有急事只能厚著臉皮麻煩不認識的聽人幫我們打電話， | F109: 突然/急事/怎麼辦/找/聽人/不認識/厚臉皮/打岔/請/幫/打電話 | G109: G1D4P1/a93｜篇章1段落1｜臺灣手語語料庫（測試版），文化部，https://tslcorpus.moc.gov.tw/ | H109: https://tslcorpus.moc.gov.tw/upload/24/web/video/QfZZoRhC0gorifom.mp4 | I109: 7d92ba71f8b795d92f964d9efaa7fb40fb0ceda520b29add64ac5bf25fde7d4a | J109: 通過 | O109: 否 | T109: =IF(J109="","未填",IF(J109="需複審",IF(OR(P109="",P109="仍需複審"),"待複審",P109),J109)) -> 通過 | U109: =IF(T109="通過",E109,IF(T109="需更正",IF(J109="需複審",IF(Q109="",E109,Q109),IF(L109="",E109,L109)),"")) -> 臨時有急事只能厚著臉皮麻煩不認識的聽人幫我們打電話， | V109: =IF(T109="通過",F109,IF(T109="需更正",IF(J109="需複審",R109,M109),"")) -> 突然/急事/怎麼辦/找/聽人/不認識/厚臉皮/打岔/請/幫/打電話 | W109: =IF(AND(OR(T109="通過",AND(T109="需更正",V109<>"")),X109="通過"),"是","否") -> 是 | X109: =IF(J109="","未填",IF(AND(J109="需複審",OR(P109="",P109="仍需複審")),"待複審",IF(OR(AND(J109="需更正",K109=""),AND(J109="需更正",M109=""),AND(J109="需更正",N109=""),AND(J109="排除",OR(K109="",N109="")),AND(J109="需複審",P109="需更正",R109=""),AND(J109="需複審",P109="需更正",S109=""),AND(J109="需複審",P109="排除",S109="")),"錯誤：請補齊必填欄位","通過"))) -> 通過
A110: TC00109 | B110: TC00109 | C110: 文化部臺灣手語語料庫 | D110: 科技 | E110: 還好大部分的人都願意幫我們， | F110: 聽人/他們/大部分/幫/願意/這 | G110: G1D4P1/a95｜篇章1段落1｜臺灣手語語料庫（測試版），文化部，https://tslcorpus.moc.gov.tw/ | H110: https://tslcorpus.moc.gov.tw/upload/24/web/video/QfZZoRhC0gorifom.mp4 | I110: 9ae53e6f606997c66a6ba1c0824f31039711ca32352b48cd0a3ca9491f56633e | J110: 需更正 | K110: 多餘詞 | M110: 聽人/他們/大部分/幫/願意 | N110: 多餘詞 | O110: 否 | T110: =IF(J110="","未填",IF(J110="需複審",IF(OR(P110="",P110="仍需複審"),"待複審",P110),J110)) -> 需更正 | U110: =IF(T110="通過",E110,IF(T110="需更正",IF(J110="需複審",IF(Q110="",E110,Q110),IF(L110="",E110,L110)),"")) -> 還好大部分的人都願意幫我們， | V110: =IF(T110="通過",F110,IF(T110="需更正",IF(J110="需複審",R110,M110),"")) -> 聽人/他們/大部分/幫/願意 | W110: =IF(AND(OR(T110="通過",AND(T110="需更正",V110<>"")),X110="通過"),"是","否") -> 是 | X110: =IF(J110="","未填",IF(AND(J110="需複審",OR(P110="",P110="仍需複審")),"待複審",IF(OR(AND(J110="需更正",K110=""),AND(J110="需更正",M110=""),AND(J110="需更正",N110=""),AND(J110="排除",OR(K110="",N110="")),AND(J110="需複審",P110="需更正",R110=""),AND(J110="需複審",P110="需更正",S110=""),AND(J110="需複審",P110="排除",S110="")),"錯誤：請補齊必填欄位","通過"))) -> 通過
A111: TC00110 | B111: TC00110 | C111: 文化部臺灣手語語料庫 | D111: 科技 | E111: 只是我覺得有點麻煩到別人很不好意思。 | F111: 不錯/麻煩/不好意思 | G111: G1D4P1/a96｜篇章1段落1｜臺灣手語語料庫（測試版），文化部，https://tslcorpus.moc.gov.tw/ | H111: https://tslcorpus.moc.gov.tw/upload/24/web/video/QfZZoRhC0gorifom.mp4 | I111: 2acdf7a86bdeaf2eed8f1db855a96c921493cf7c36dcfa04390a674636c35198 | J111: 需更正 | K111: 多餘詞 | M111: 麻煩/不好意思 | N111: 多餘詞 | O111: 否 | T111: =IF(J111="","未填",IF(J111="需複審",IF(OR(P111="",P111="仍需複審"),"待複審",P111),J111)) -> 需更正 | U111: =IF(T111="通過",E111,IF(T111="需更正",IF(J111="需複審",IF(Q111="",E111,Q111),IF(L111="",E111,L111)),"")) -> 只是我覺得有點麻煩到別人很不好意思。 | V111: =IF(T111="通過",F111,IF(T111="需更正",IF(J111="需複審",R111,M111),"")) -> 麻煩/不好意思 | W111: =IF(AND(OR(T111="通過",AND(T111="需更正",V111<>"")),X111="通過"),"是","否") -> 是 | X111: =IF(J111="","未填",IF(AND(J111="需複審",OR(P111="",P111="仍需複審")),"待複審",IF(OR(AND(J111="需更正",K111=""),AND(J111="需更正",M111=""),AND(J111="需更正",N111=""),AND(J111="排除",OR(K111="",N111="")),AND(J111="需複審",P111="需更正",R111=""),AND(J111="需複審",P111="需更正",S111=""),AND(J111="需複審",P111="排除",S111="")),"錯誤：請補齊必填欄位","通過"))) -> 通過
A112: TC00111 | B112: TC00111 | C112: 文化部臺灣手語語料庫 | D112: 社會 | E112: 每逢總統選舉的時候， | F112: 總統/選舉/接近 | G112: G2D3P1/a167｜篇章1段落1｜臺灣手語語料庫（測試版），文化部，https://tslcorpus.moc.gov.tw/ | H112: https://tslcorpus.moc.gov.tw/upload/24/web/video/997aRoIBdZ2HMFt5.mp4 | I112: 27c8c20509457074fbb6469397b3b277a2531d186f75039a53f7eedb09bebced | J112: 通過 | O112: 否 | T112: =IF(J112="","未填",IF(J112="需複審",IF(OR(P112="",P112="仍需複審"),"待複審",P112),J112)) -> 通過 | U112: =IF(T112="通過",E112,IF(T112="需更正",IF(J112="需複審",IF(Q112="",E112,Q112),IF(L112="",E112,L112)),"")) -> 每逢總統選舉的時候， | V112: =IF(T112="通過",F112,IF(T112="需更正",IF(J112="需複審",R112,M112),"")) -> 總統/選舉/接近 | W112: =IF(AND(OR(T112="通過",AND(T112="需更正",V112<>"")),X112="通過"),"是","否") -> 是 | X112: =IF(J112="","未填",IF(AND(J112="需複審",OR(P112="",P112="仍需複審")),"待複審",IF(OR(AND(J112="需更正",K112=""),AND(J112="需更正",M112=""),AND(J112="需更正",N112=""),AND(J112="排除",OR(K112="",N112="")),AND(J112="需複審",P112="需更正",R112=""),AND(J112="需複審",P112="需更正",S112=""),AND(J112="需複審",P112="排除",S112="")),"錯誤：請補齊必填欄位","通過"))) -> 通過
A113: TC00112 | B113: TC00112 | C113: 文化部臺灣手語語料庫 | D113: 社會 | E113: 我會注意正副總統候選人名單。 | F113: 總統/正/副/候選人/他們兩個/名字/誰/我/注意/會 | G113: G2D3P1/a168｜篇章1段落1｜臺灣手語語料庫（測試版），文化部，https://tslcorpus.moc.gov.tw/ | H113: https://tslcorpus.moc.gov.tw/upload/24/web/video/997aRoIBdZ2HMFt5.mp4 | I113: ec9bdf2e77df6d2cf119ef1a4938c64b942f704a170bbadf44b1e8fab1b44cf2 | J113: 通過 | O113: 否 | T113: =IF(J113="","未填",IF(J113="需複審",IF(OR(P113="",P113="仍需複審"),"待複審",P113),J113)) -> 通過 | U113: =IF(T113="通過",E113,IF(T113="需更正",IF(J113="需複審",IF(Q113="",E113,Q113),IF(L113="",E113,L113)),"")) -> 我會注意正副總統候選人名單。 | V113: =IF(T113="通過",F113,IF(T113="需更正",IF(J113="需複審",R113,M113),"")) -> 總統/正/副/候選人/他們兩個/名字/誰/我/注意/會 | W113: =IF(AND(OR(T113="通過",AND(T113="需更正",V113<>"")),X113="通過"),"是","否") -> 是 | X113: =IF(J113="","未填",IF(AND(J113="需複審",OR(P113="",P113="仍需複審")),"待複審",IF(OR(AND(J113="需更正",K113=""),AND(J113="需更正",M113=""),AND(J113="需更正",N113=""),AND(J113="排除",OR(K113="",N113="")),AND(J113="需複審",P113="需更正",R113=""),AND(J113="需複審",P113="需更正",S113=""),AND(J113="需複審",P113="排除",S113="")),"錯誤：請補齊必填欄位","通過"))) -> 通過
A114: TC00113 | B114: TC00113 | C114: 文化部臺灣手語語料庫 | D114: 社會 | E114: 我有收到政府寄發的候選人政見發表公報， | F114: 候選人/政見/公報/政府/發放/我/拿/有 | G114: G2D3P1/a169｜篇章1段落1｜臺灣手語語料庫（測試版），文化部，https://tslcorpus.moc.gov.tw/ | H114: https://tslcorpus.moc.gov.tw/upload/24/web/video/997aRoIBdZ2HMFt5.mp4 | I114: 6954c3af2a7a7bc794fd803ed46d08a2fecf020a6911a6f655e338fd66deec70 | J114: 通過 | O114: 否 | T114: =IF(J114="","未填",IF(J114="需複審",IF(OR(P114="",P114="仍需複審"),"待複審",P114),J114)) -> 通過 | U114: =IF(T114="通過",E114,IF(T114="需更正",IF(J114="需複審",IF(Q114="",E114,Q114),IF(L114="",E114,L114)),"")) -> 我有收到政府寄發的候選人政見發表公報， | V114: =IF(T114="通過",F114,IF(T114="需更正",IF(J114="需複審",R114,M114),"")) -> 候選人/政見/公報/政府/發放/我/拿/有 | W114: =IF(AND(OR(T114="通過",AND(T114="需更正",V114<>"")),X114="通過"),"是","否") -> 是 | X114: =IF(J114="","未填",IF(AND(J114="需複審",OR(P114="",P114="仍需複審")),"待複審",IF(OR(AND(J114="需更正",K114=""),AND(J114="需更正",M114=""),AND(J114="需更正",N114=""),AND(J114="排除",OR(K114="",N114="")),AND(J114="需複審",P114="需更正",R114=""),AND(J114="需複審",P114="需更正",S114=""),AND(J114="需複審",P114="排除",S114="")),"錯誤：請補齊必填欄位","通過"))) -> 通過
A115: TC00114 | B115: TC00114 | C115: 文化部臺灣手語語料庫 | D115: 社會 | E115: 但文字太多， | F115: 但是/字/多 | G115: G2D3P1/a170｜篇章1段落1｜臺灣手語語料庫（測試版），文化部，https://tslcorpus.moc.gov.tw/ | H115: https://tslcorpus.moc.gov.tw/upload/24/web/video/997aRoIBdZ2HMFt5.mp4 | I115: ab2b06a9392760cb4cd63cb5e97b009aaf860393e9d029f33c0a7de2ad367f93 | J115: 通過 | O115: 否 | T115: =IF(J115="","未填",IF(J115="需複審",IF(OR(P115="",P115="仍需複審"),"待複審",P115),J115)) -> 通過 | U115: =IF(T115="通過",E115,IF(T115="需更正",IF(J115="需複審",IF(Q115="",E115,Q115),IF(L115="",E115,L115)),"")) -> 但文字太多， | V115: =IF(T115="通過",F115,IF(T115="需更正",IF(J115="需複審",R115,M115),"")) -> 但是/字/多 | W115: =IF(AND(OR(T115="通過",AND(T115="需更正",V115<>"")),X115="通過"),"是","否") -> 是 | X115: =IF(J115="","未填",IF(AND(J115="需複審",OR(P115="",P115="仍需複審")),"待複審",IF(OR(AND(J115="需更正",K115=""),AND(J115="需更正",M115=""),AND(J115="需更正",N115=""),AND(J115="排除",OR(K115="",N115="")),AND(J115="需複審",P115="需更正",R115=""),AND(J115="需複審",P115="需更正",S115=""),AND(J115="需複審",P115="排除",S115="")),"錯誤：請補齊必填欄位","通過"))) -> 通過
A116: TC00115 | B116: TC00115 | C116: 文化部臺灣手語語料庫 | D116: 社會 | E116: 令人眼花撩亂。 | F116: 閱讀/眼花撩亂 | G116: G2D3P1/a1075｜篇章1段落1｜臺灣手語語料庫（測試版），文化部，https://tslcorpus.moc.gov.tw/ | H116: https://tslcorpus.moc.gov.tw/upload/24/web/video/997aRoIBdZ2HMFt5.mp4 | I116: b2a7d082af079b539ba36e11bd0f81f27faf0df62d7fdc99d82e9d82899aa960 | J116: 通過 | O116: 否 | T116: =IF(J116="","未填",IF(J116="需複審",IF(OR(P116="",P116="仍需複審"),"待複審",P116),J116)) -> 通過 | U116: =IF(T116="通過",E116,IF(T116="需更正",IF(J116="需複審",IF(Q116="",E116,Q116),IF(L116="",E116,L116)),"")) -> 令人眼花撩亂。 | V116: =IF(T116="通過",F116,IF(T116="需更正",IF(J116="需複審",R116,M116),"")) -> 閱讀/眼花撩亂 | W116: =IF(AND(OR(T116="通過",AND(T116="需更正",V116<>"")),X116="通過"),"是","否") -> 是 | X116: =IF(J116="","未填",IF(AND(J116="需複審",OR(P116="",P116="仍需複審")),"待複審",IF(OR(AND(J116="需更正",K116=""),AND(J116="需更正",M116=""),AND(J116="需更正",N116=""),AND(J116="排除",OR(K116="",N116="")),AND(J116="需複審",P116="需更正",R116=""),AND(J116="需複審",P116="需更正",S116=""),AND(J116="需複審",P116="排除",S116="")),"錯誤：請補齊必填欄位","通過"))) -> 通過
A117: TC00116 | B117: TC00116 | C117: 文化部臺灣手語語料庫 | D117: 社會 | E117: 我反而喜歡看電視總統政見發表會， | F117: 電視/總統/政見發表會/這/棒/我/喜歡 | G117: G2D3P1/a171｜篇章1段落1｜臺灣手語語料庫（測試版），文化部，https://tslcorpus.moc.gov.tw/ | H117: https://tslcorpus.moc.gov.tw/upload/24/web/video/997aRoIBdZ2HMFt5.mp4 | I117: b999499c87d4a8a3c9cb418d8d9386f3f06e3d92f171fbe2a17ba846f97429f0 | J117: 通過 | O117: 否 | T117: =IF(J117="","未填",IF(J117="需複審",IF(OR(P117="",P117="仍需複審"),"待複審",P117),J117)) -> 通過 | U117: =IF(T117="通過",E117,IF(T117="需更正",IF(J117="需複審",IF(Q117="",E117,Q117),IF(L117="",E117,L117)),"")) -> 我反而喜歡看電視總統政見發表會， | V117: =IF(T117="通過",F117,IF(T117="需更正",IF(J117="需複審",R117,M117),"")) -> 電視/總統/政見發表會/這/棒/我/喜歡 | W117: =IF(AND(OR(T117="通過",AND(T117="需更正",V117<>"")),X117="通過"),"是","否") -> 是 | X117: =IF(J117="","未填",IF(AND(J117="需複審",OR(P117="",P117="仍需複審")),"待複審",IF(OR(AND(J117="需更正",K117=""),AND(J117="需更正",M117=""),AND(J117="需更正",N117=""),AND(J117="排除",OR(K117="",N117="")),AND(J117="需複審",P117="需更正",R117=""),AND(J117="需複審",P117="需更正",S117=""),AND(J117="需複審",P117="排除",S117="")),"錯誤：請補齊必填欄位","通過"))) -> 通過
A118: TC00117 | B118: TC00117 | C118: 文化部臺灣手語語料庫 | D118: 社會 | E118: 每位候選人能在政見發表上詳細敘述， | F118: 候選人/演講/解釋/仔細/能 | G118: G2D3P1/a172｜篇章1段落1｜臺灣手語語料庫（測試版），文化部，https://tslcorpus.moc.gov.tw/ | H118: https://tslcorpus.moc.gov.tw/upload/24/web/video/997aRoIBdZ2HMFt5.mp4 | I118: b30d45676a7cd432ba00bf2820aaa03401f9dd95c71effaedb31b587a83f339a | J118: 通過 | O118: 否 | T118: =IF(J118="","未填",IF(J118="需複審",IF(OR(P118="",P118="仍需複審"),"待複審",P118),J118)) -> 通過 | U118: =IF(T118="通過",E118,IF(T118="需更正",IF(J118="需複審",IF(Q118="",E118,Q118),IF(L118="",E118,L118)),"")) -> 每位候選人能在政見發表上詳細敘述， | V118: =IF(T118="通過",F118,IF(T118="需更正",IF(J118="需複審",R118,M118),"")) -> 候選人/演講/解釋/仔細/能 | W118: =IF(AND(OR(T118="通過",AND(T118="需更正",V118<>"")),X118="通過"),"是","否") -> 是 | X118: =IF(J118="","未填",IF(AND(J118="需複審",OR(P118="",P118="仍需複審")),"待複審",IF(OR(AND(J118="需更正",K118=""),AND(J118="需更正",M118=""),AND(J118="需更正",N118=""),AND(J118="排除",OR(K118="",N118="")),AND(J118="需複審",P118="需更正",R118=""),AND(J118="需複審",P118="需更正",S118=""),AND(J118="需複審",P118="排除",S118="")),"錯誤：請補齊必填欄位","通過"))) -> 通過
A119: TC00118 | B119: TC00118 | C119: 文化部臺灣手語語料庫 | D119: 社會 | E119: 我會留意哪位候選人提出的身心障礙福利政策比較好， | F119: 身心障礙/福利/政府/計畫/提出/演講/比較/棒/誰/我/注意/會 | G119: G2D3P1/a173｜篇章1段落1｜臺灣手語語料庫（測試版），文化部，https://tslcorpus.moc.gov.tw/ | H119: https://tslcorpus.moc.gov.tw/upload/24/web/video/997aRoIBdZ2HMFt5.mp4 | I119: 0b7b2ef8b7777f209514d10b63b2742c94fa95f281b4a6043c1fbde960e8293d | J119: 通過 | O119: 否 | T119: =IF(J119="","未填",IF(J119="需複審",IF(OR(P119="",P119="仍需複審"),"待複審",P119),J119)) -> 通過 | U119: =IF(T119="通過",E119,IF(T119="需更正",IF(J119="需複審",IF(Q119="",E119,Q119),IF(L119="",E119,L119)),"")) -> 我會留意哪位候選人提出的身心障礙福利政策比較好， | V119: =IF(T119="通過",F119,IF(T119="需更正",IF(J119="需複審",R119,M119),"")) -> 身心障礙/福利/政府/計畫/提出/演講/比較/棒/誰/我/注意/會 | W119: =IF(AND(OR(T119="通過",AND(T119="需更正",V119<>"")),X119="通過"),"是","否") -> 是 | X119: =IF(J119="","未填",IF(AND(J119="需複審",OR(P119="",P119="仍需複審")),"待複審",IF(OR(AND(J119="需更正",K119=""),AND(J119="需更正",M119=""),AND(J119="需更正",N119=""),AND(J119="排除",OR(K119="",N119="")),AND(J119="需複審",P119="需更正",R119=""),AND(J119="需複審",P119="需更正",S119=""),AND(J119="需複審",P119="排除",S119="")),"錯誤：請補齊必填欄位","通過"))) -> 通過
A120: TC00119 | B120: TC00119 | C120: 文化部臺灣手語語料庫 | D120: 社會 | E120: 我也喜歡看他們交互詰問， 可以知道他們機智應變的能力如何。 | F120: 再/候選人/問答/辯論/觀賞/我/喜歡/他們/聰明/想/能力/好不好/我/看透/知道/可以 | G120: G2D3P1/a174｜篇章1段落1｜臺灣手語語料庫（測試版），文化部，https://tslcorpus.moc.gov.tw/ | H120: https://tslcorpus.moc.gov.tw/upload/24/web/video/997aRoIBdZ2HMFt5.mp4 | I120: 0d68bc0c6fbefdde084d026bed937aa358a04b876f57ba8269a563ff56b5f9e5 | J120: 通過 | O120: 否 | T120: =IF(J120="","未填",IF(J120="需複審",IF(OR(P120="",P120="仍需複審"),"待複審",P120),J120)) -> 通過 | U120: =IF(T120="通過",E120,IF(T120="需更正",IF(J120="需複審",IF(Q120="",E120,Q120),IF(L120="",E120,L120)),"")) -> 我也喜歡看他們交互詰問， 可以知道他們機智應變的能力如何。 | V120: =IF(T120="通過",F120,IF(T120="需更正",IF(J120="需複審",R120,M120),"")) -> 再/候選人/問答/辯論/觀賞/我/喜歡/他們/聰明/想/能力/好不好/我/看透/知道/可以 | W120: =IF(AND(OR(T120="通過",AND(T120="需更正",V120<>"")),X120="通過"),"是","否") -> 是 | X120: =IF(J120="","未填",IF(AND(J120="需複審",OR(P120="",P120="仍需複審")),"待複審",IF(OR(AND(J120="需更正",K120=""),AND(J120="需更正",M120=""),AND(J120="需更正",N120=""),AND(J120="排除",OR(K120="",N120="")),AND(J120="需複審",P120="需更正",R120=""),AND(J120="需複審",P120="需更正",S120=""),AND(J120="需複審",P120="排除",S120="")),"錯誤：請補齊必填欄位","通過"))) -> 通過
A121: TC00120 | B121: TC00120 | C121: 文化部臺灣手語語料庫 | D121: 社會 | E121: 以前政見發表會電視上的手語翻譯畫面很小， | F121: 以前/政見發表會/電視/手語翻譯/電視+畫面縮小 | G121: G2D3P1/a176｜篇章1段落1｜臺灣手語語料庫（測試版），文化部，https://tslcorpus.moc.gov.tw/ | H121: https://tslcorpus.moc.gov.tw/upload/24/web/video/997aRoIBdZ2HMFt5.mp4 | I121: 6e9d13d955124dd8d28458e708d71fdcd73c06bb9abe7b4db10f28836f879bf2 | J121: 通過 | O121: 否 | T121: =IF(J121="","未填",IF(J121="需複審",IF(OR(P121="",P121="仍需複審"),"待複審",P121),J121)) -> 通過 | U121: =IF(T121="通過",E121,IF(T121="需更正",IF(J121="需複審",IF(Q121="",E121,Q121),IF(L121="",E121,L121)),"")) -> 以前政見發表會電視上的手語翻譯畫面很小， | V121: =IF(T121="通過",F121,IF(T121="需更正",IF(J121="需複審",R121,M121),"")) -> 以前/政見發表會/電視/手語翻譯/電視+畫面縮小 | W121: =IF(AND(OR(T121="通過",AND(T121="需更正",V121<>"")),X121="通過"),"是","否") -> 是 | X121: =IF(J121="","未填",IF(AND(J121="需複審",OR(P121="",P121="仍需複審")),"待複審",IF(OR(AND(J121="需更正",K121=""),AND(J121="需更正",M121=""),AND(J121="需更正",N121=""),AND(J121="排除",OR(K121="",N121="")),AND(J121="需複審",P121="需更正",R121=""),AND(J121="需複審",P121="需更正",S121=""),AND(J121="需複審",P121="排除",S121="")),"錯誤：請補齊必填欄位","通過"))) -> 通過
A122: TC00121 | B122: TC00121 | C122: 文化部臺灣手語語料庫 | D122: 社會 | E122: 既模糊又不清楚， | F122: 電視+看/不清楚/模糊 | G122: G2D3P1/a1076｜篇章1段落1｜臺灣手語語料庫（測試版），文化部，https://tslcorpus.moc.gov.tw/ | H122: https://tslcorpus.moc.gov.tw/upload/24/web/video/997aRoIBdZ2HMFt5.mp4 | I122: 4e2b5b44b65cfbea562d5ef4db4e9a25cc1ad270df3200dfd7cd85f67ffb147f | J122: 通過 | O122: 否 | T122: =IF(J122="","未填",IF(J122="需複審",IF(OR(P122="",P122="仍需複審"),"待複審",P122),J122)) -> 通過 | U122: =IF(T122="通過",E122,IF(T122="需更正",IF(J122="需複審",IF(Q122="",E122,Q122),IF(L122="",E122,L122)),"")) -> 既模糊又不清楚， | V122: =IF(T122="通過",F122,IF(T122="需更正",IF(J122="需複審",R122,M122),"")) -> 電視+看/不清楚/模糊 | W122: =IF(AND(OR(T122="通過",AND(T122="需更正",V122<>"")),X122="通過"),"是","否") -> 是 | X122: =IF(J122="","未填",IF(AND(J122="需複審",OR(P122="",P122="仍需複審")),"待複審",IF(OR(AND(J122="需更正",K122=""),AND(J122="需更正",M122=""),AND(J122="需更正",N122=""),AND(J122="排除",OR(K122="",N122="")),AND(J122="需複審",P122="需更正",R122=""),AND(J122="需複審",P122="需更正",S122=""),AND(J122="需複審",P122="排除",S122="")),"錯誤：請補齊必填欄位","通過"))) -> 通過
A123: TC00122 | B123: TC00122 | C123: 文化部臺灣手語語料庫 | D123: 社會 | E123: 我都會搬椅子到電視前面就近看， | F123: 我/椅子拉近/觀賞 | G123: G2D3P1/a177｜篇章1段落1｜臺灣手語語料庫（測試版），文化部，https://tslcorpus.moc.gov.tw/ | H123: https://tslcorpus.moc.gov.tw/upload/24/web/video/997aRoIBdZ2HMFt5.mp4 | I123: c1ea6ae6a17847178331e722062baea8710aa857df35ee93cb3df54a32d49882 | J123: 通過 | O123: 否 | T123: =IF(J123="","未填",IF(J123="需複審",IF(OR(P123="",P123="仍需複審"),"待複審",P123),J123)) -> 通過 | U123: =IF(T123="通過",E123,IF(T123="需更正",IF(J123="需複審",IF(Q123="",E123,Q123),IF(L123="",E123,L123)),"")) -> 我都會搬椅子到電視前面就近看， | V123: =IF(T123="通過",F123,IF(T123="需更正",IF(J123="需複審",R123,M123),"")) -> 我/椅子拉近/觀賞 | W123: =IF(AND(OR(T123="通過",AND(T123="需更正",V123<>"")),X123="通過"),"是","否") -> 是 | X123: =IF(J123="","未填",IF(AND(J123="需複審",OR(P123="",P123="仍需複審")),"待複審",IF(OR(AND(J123="需更正",K123=""),AND(J123="需更正",M123=""),AND(J123="需更正",N123=""),AND(J123="排除",OR(K123="",N123="")),AND(J123="需複審",P123="需更正",R123=""),AND(J123="需複審",P123="需更正",S123=""),AND(J123="需複審",P123="排除",S123="")),"錯誤：請補齊必填欄位","通過"))) -> 通過
... A130: TC00129 | B130: TC00129 | C130: 文化部臺灣手語語料庫 | D130: 情緒態度 | E130: 我的好朋友有一對雙胞胎女兒， | F130: 我/好/朋友/雙胞胎/大女兒/小女兒 | G130: G3D2P1/a80｜篇章1段落1｜臺灣手語語料庫（測試版），文化部，https://tslcorpus.moc.gov.tw/ | H130: https://tslcorpus.moc.gov.tw/upload/24/web/video/ObWmrbd2FxgPwwqL.mp4 | I130: 9408c29b7769862ec4f27ef4ed8638bc608e5915318a6fef3e200affc457b9dc | J130: 通過 | O130: 否 | T130: =IF(J130="","未填",IF(J130="需複審",IF(OR(P130="",P130="仍需複審"),"待複審",P130),J130)) -> 通過 | U130: =IF(T130="通過",E130,IF(T130="需更正",IF(J130="需複審",IF(Q130="",E130,Q130),IF(L130="",E130,L130)),"")) -> 我的好朋友有一對雙胞胎女兒， | V130: =IF(T130="通過",F130,IF(T130="需更正",IF(J130="需複審",R130,M130),"")) -> 我/好/朋友/雙胞胎/大女兒/小女兒 | W130: =IF(AND(OR(T130="通過",AND(T130="需更正",V130<>"")),X130="通過"),"是","否") -> 是 | X130: =IF(J130="","未填",IF(AND(J130="需複審",OR(P130="",P130="仍需複審")),"待複審",IF(OR(AND(J130="需更正",K130=""),AND(J130="需更正",M130=""),AND(J130="需更正",N130=""),AND(J130="排除",OR(K130="",N130="")),AND(J130="需複審",P130="需更正",R130=""),AND(J130="需複審",P130="需更正",S130=""),AND(J130="需複審",P130="排除",S130="")),"錯誤：請補齊必填欄位","通過"))) -> 通過
A131: TC00130 | B131: TC00130 | C131: 文化部臺灣手語語料庫 | D131: 情緒態度 | E131: 兩個女兒個性不一樣。 | F131: 他們兩個/個性 | G131: G3D2P1/a81｜篇章1段落1｜臺灣手語語料庫（測試版），文化部，https://tslcorpus.moc.gov.tw/ | H131: https://tslcorpus.moc.gov.tw/upload/24/web/video/ObWmrbd2FxgPwwqL.mp4 | I131: aa00fa1bbeac36e3a5f0292f9616aabafa9db154ef34a4f4aa31c46e5d252059 | J131: 需更正 | K131: 漏詞 | M131: 他們兩個/個性/不一樣 | N131: 漏詞 | O131: 否 | T131: =IF(J131="","未填",IF(J131="需複審",IF(OR(P131="",P131="仍需複審"),"待複審",P131),J131)) -> 需更正 | U131: =IF(T131="通過",E131,IF(T131="需更正",IF(J131="需複審",IF(Q131="",E131,Q131),IF(L131="",E131,L131)),"")) -> 兩個女兒個性不一樣。 | V131: =IF(T131="通過",F131,IF(T131="需更正",IF(J131="需複審",R131,M131),"")) -> 他們兩個/個性/不一樣 | W131: =IF(AND(OR(T131="通過",AND(T131="需更正",V131<>"")),X131="通過"),"是","否") -> 是 | X131: =IF(J131="","未填",IF(AND(J131="需複審",OR(P131="",P131="仍需複審")),"待複審",IF(OR(AND(J131="需更正",K131=""),AND(J131="需更正",M131=""),AND(J131="需更正",N131=""),AND(J131="排除",OR(K131="",N131="")),AND(J131="需複審",P131="需更正",R131=""),AND(J131="需複審",P131="需更正",S131=""),AND(J131="需複審",P131="排除",S131="")),"錯誤：請補齊必填欄位","通過"))) -> 通過
A132: TC00131 | B132: TC00131 | C132: 文化部臺灣手語語料庫 | D132: 情緒態度 | E132: 大女兒活潑外向不怕生， | F132: 不一樣/大女兒/個性/活潑/碰到/陌生/不怕 | G132: G3D2P1/a82｜篇章1段落1｜臺灣手語語料庫（測試版），文化部，https://tslcorpus.moc.gov.tw/ | H132: https://tslcorpus.moc.gov.tw/upload/24/web/video/ObWmrbd2FxgPwwqL.mp4 | I132: f1ed733c689cf5082de1c730dee40778b5c1b156468a961747460a1a3e80922a | J132: 需更正 | K132: 多餘詞 | M132: 大女兒/個性/活潑/碰到/陌生/不怕 | N132: 多餘詞 | O132: 否 | T132: =IF(J132="","未填",IF(J132="需複審",IF(OR(P132="",P132="仍需複審"),"待複審",P132),J132)) -> 需更正 | U132: =IF(T132="通過",E132,IF(T132="需更正",IF(J132="需複審",IF(Q132="",E132,Q132),IF(L132="",E132,L132)),"")) -> 大女兒活潑外向不怕生， | V132: =IF(T132="通過",F132,IF(T132="需更正",IF(J132="需複審",R132,M132),"")) -> 大女兒/個性/活潑/碰到/陌生/不怕 | W132: =IF(AND(OR(T132="通過",AND(T132="需更正",V132<>"")),X132="通過"),"是","否") -> 是 | X132: =IF(J132="","未填",IF(AND(J132="需複審",OR(P132="",P132="仍需複審")),"待複審",IF(OR(AND(J132="需更正",K132=""),AND(J132="需更正",M132=""),AND(J132="需更正",N132=""),AND(J132="排除",OR(K132="",N132="")),AND(J132="需複審",P132="需更正",R132=""),AND(J132="需複審",P132="需更正",S132=""),AND(J132="需複審",P132="排除",S132="")),"錯誤：請補齊必填欄位","通過"))) -> 通過
A133: TC00132 | B133: TC00132 | C133: 文化部臺灣手語語料庫 | D133: 情緒態度 | E133: 喜歡結交朋友。 | F133: 朋友/交往/喜歡 | G133: G3D2P1/a83｜篇章1段落1｜臺灣手語語料庫（測試版），文化部，https://tslcorpus.moc.gov.tw/ | H133: https://tslcorpus.moc.gov.tw/upload/24/web/video/ObWmrbd2FxgPwwqL.mp4 | I133: 32edb9b54d35b169ff5c920aa83b0d127e845b1e84c948c16f854abd6fa46923 | J133: 通過 | O133: 否 | T133: =IF(J133="","未填",IF(J133="需複審",IF(OR(P133="",P133="仍需複審"),"待複審",P133),J133)) -> 通過 | U133: =IF(T133="通過",E133,IF(T133="需更正",IF(J133="需複審",IF(Q133="",E133,Q133),IF(L133="",E133,L133)),"")) -> 喜歡結交朋友。 | V133: =IF(T133="通過",F133,IF(T133="需更正",IF(J133="需複審",R133,M133),"")) -> 朋友/交往/喜歡 | W133: =IF(AND(OR(T133="通過",AND(T133="需更正",V133<>"")),X133="通過"),"是","否") -> 是 | X133: =IF(J133="","未填",IF(AND(J133="需複審",OR(P133="",P133="仍需複審")),"待複審",IF(OR(AND(J133="需更正",K133=""),AND(J133="需更正",M133=""),AND(J133="需更正",N133=""),AND(J133="排除",OR(K133="",N133="")),AND(J133="需複審",P133="需更正",R133=""),AND(J133="需複審",P133="需更正",S133=""),AND(J133="需複審",P133="排除",S133="")),"錯誤：請補齊必填欄位","通過"))) -> 通過
A134: TC00133 | B134: TC00133 | C134: 文化部臺灣手語語料庫 | D134: 情緒態度 | E134: 她熱愛冒險和刺激， | F134: 她/冒險/刺激/喜歡 | G134: G3D2P1/a84｜篇章1段落1｜臺灣手語語料庫（測試版），文化部，https://tslcorpus.moc.gov.tw/ | H134: https://tslcorpus.moc.gov.tw/upload/24/web/video/ObWmrbd2FxgPwwqL.mp4 | I134: ec346bb7df18d1ae376d94f486d3ac51ab07e4f81c906db8511bd63ade8cee18 | J134: 通過 | O134: 否 | T134: =IF(J134="","未填",IF(J134="需複審",IF(OR(P134="",P134="仍需複審"),"待複審",P134),J134)) -> 通過 | U134: =IF(T134="通過",E134,IF(T134="需更正",IF(J134="需複審",IF(Q134="",E134,Q134),IF(L134="",E134,L134)),"")) -> 她熱愛冒險和刺激， | V134: =IF(T134="通過",F134,IF(T134="需更正",IF(J134="需複審",R134,M134),"")) -> 她/冒險/刺激/喜歡 | W134: =IF(AND(OR(T134="通過",AND(T134="需更正",V134<>"")),X134="通過"),"是","否") -> 是 | X134: =IF(J134="","未填",IF(AND(J134="需複審",OR(P134="",P134="仍需複審")),"待複審",IF(OR(AND(J134="需更正",K134=""),AND(J134="需更正",M134=""),AND(J134="需更正",N134=""),AND(J134="排除",OR(K134="",N134="")),AND(J134="需複審",P134="需更正",R134=""),AND(J134="需複審",P134="需更正",S134=""),AND(J134="需複審",P134="排除",S134="")),"錯誤：請補齊必填欄位","通過"))) -> 通過
A135: TC00134 | B135: TC00134 | C135: 文化部臺灣手語語料庫 | D135: 情緒態度 | E135: 常常求媽媽幫她報名攀岩、獨木舟、露營等活動。 | F135: 常常/請求/媽媽/幫忙/報名/攀岩/獨木舟/露營/種類 | G135: G3D2P1/a85｜篇章1段落1｜臺灣手語語料庫（測試版），文化部，https://tslcorpus.moc.gov.tw/ | H135: https://tslcorpus.moc.gov.tw/upload/24/web/video/ObWmrbd2FxgPwwqL.mp4 | I135: b643ac48a42974300d29e8ec446b6a2719bd90a29f70cae6f5d02741a39497cf | J135: 通過 | O135: 否 | T135: =IF(J135="","未填",IF(J135="需複審",IF(OR(P135="",P135="仍需複審"),"待複審",P135),J135)) -> 通過 | U135: =IF(T135="通過",E135,IF(T135="需更正",IF(J135="需複審",IF(Q135="",E135,Q135),IF(L135="",E135,L135)),"")) -> 常常求媽媽幫她報名攀岩、獨木舟、露營等活動。 | V135: =IF(T135="通過",F135,IF(T135="需更正",IF(J135="需複審",R135,M135),"")) -> 常常/請求/媽媽/幫忙/報名/攀岩/獨木舟/露營/種類 | W135: =IF(AND(OR(T135="通過",AND(T135="需更正",V135<>"")),X135="通過"),"是","否") -> 是 | X135: =IF(J135="","未填",IF(AND(J135="需複審",OR(P135="",P135="仍需複審")),"待複審",IF(OR(AND(J135="需更正",K135=""),AND(J135="需更正",M135=""),AND(J135="需更正",N135=""),AND(J135="排除",OR(K135="",N135="")),AND(J135="需複審",P135="需更正",R135=""),AND(J135="需複審",P135="需更正",S135=""),AND(J135="需複審",P135="排除",S135="")),"錯誤：請補齊必填欄位","通過"))) -> 通過
A136: TC00135 | B136: TC00135 | C136: 文化部臺灣手語語料庫 | D136: 公共服務 | E136: 那位朋友因為聽力下降的緣故， | F136: 朋友/那/聽力/漸減 | G136: G2D1P2/a61｜篇章1段落2｜臺灣手語語料庫（測試版），文化部，https://tslcorpus.moc.gov.tw/ | H136: https://tslcorpus.moc.gov.tw/upload/24/web/video/hkB12Mug40BSZCoX.mp4 | I136: a8e6e816490d758c6f333036fd653520b3466b7ac081e1afbdb10ce1384857f8 | J136: 通過 | O136: 否 | T136: =IF(J136="","未填",IF(J136="需複審",IF(OR(P136="",P136="仍需複審"),"待複審",P136),J136)) -> 通過 | U136: =IF(T136="通過",E136,IF(T136="需更正",IF(J136="需複審",IF(Q136="",E136,Q136),IF(L136="",E136,L136)),"")) -> 那位朋友因為聽力下降的緣故， | V136: =IF(T136="通過",F136,IF(T136="需更正",IF(J136="需複審",R136,M136),"")) -> 朋友/那/聽力/漸減 | W136: =IF(AND(OR(T136="通過",AND(T136="需更正",V136<>"")),X136="通過"),"是","否") -> 是 | X136: =IF(J136="","未填",IF(AND(J136="需複審",OR(P136="",P136="仍需複審")),"待複審",IF(OR(AND(J136="需更正",K136=""),AND(J136="需更正",M136=""),AND(J136="需更正",N136=""),AND(J136="排除",OR(K136="",N136="")),AND(J136="需複審",P136="需更正",R136=""),AND(J136="需複審",P136="需更正",S136=""),AND(J136="需複審",P136="排除",S136="")),"錯誤：請補齊必填欄位","通過"))) -> 通過
...

Sheet 進度統計
A1: 文化部臺灣手語語料庫｜校訂進度
A3: 指標 | B3: 數量
A4: 總筆數 | B4: =COUNTA(人工校訂!$A$2:$A$5126) -> 5125
A5: 未填 | B5: =COUNTIF(人工校訂!$T$2:$T$5126,"未填") -> 0
A6: 通過 | B6: =COUNTIF(人工校訂!$T$2:$T$5126,"通過") -> 4580
A7: 需更正 | B7: =COUNTIF(人工校訂!$T$2:$T$5126,"需更正") -> 527
A8: 排除 | B8: =COUNTIF(人工校訂!$T$2:$T$5126,"排除") -> 18
A9: 待複審 | B9: =COUNTIF(人工校訂!$T$2:$T$5126,"待複審") -> 0
A10: 可匯入訓練 | B10: =COUNTIF(人工校訂!$W$2:$W$5126,"是") -> 5107
A11: 需影片確認 | B11: =COUNTIF(人工校訂!$O$2:$O$5126,"是") -> 0
A12: 資料檢查錯誤 | B12: =COUNTIF(人工校訂!$X$2:$X$5126,"錯誤*") -> 0
A14: 使用提示
A15: 進度會依「人工校訂」中的判定自動更新。
A16: 只有「可匯入訓練＝是」且「資料檢查結果＝通過」的列，才適合日後轉為訓練資料。

Sheet 欄位選項
A1: 主審判定 | B1: 複審判定 | C1: 問題類型 | D1: 需影片確認
A2: 通過 | B2: 通過 | C2: 中文語意錯誤 | D2: 否
A3: 需更正 | B3: 需更正 | C3: Gloss詞彙錯誤 | D3: 是
A4: 排除 | B4: 排除 | C4: Gloss語序錯誤
A5: 需複審 | B5: 仍需複審 | C5: 漏詞
C6: 多餘詞
C7: 拼寫或格式問題
C8: 中文與Gloss不對應
C9: 重複或資料衝突
C10: 需影片或上下文確認
C11: 其他
